{
"meta":{"test_sets":[],"test_metrics":[],"learn_metrics":[{"best_value":"Min","name":"RMSE"}],"launch_mode":"Train","parameters":"","iteration_count":1000,"learn_sets":["learn"],"name":"experiment"},
"iterations":[
{"learn":[14.9127897],"iteration":0,"passed_time":0.0009611417055,"remaining_time":0.9601805638},
{"learn":[14.8135308],"iteration":1,"passed_time":0.001858644793,"remaining_time":0.9274637518},
{"learn":[14.71552767],"iteration":2,"passed_time":0.002677289499,"remaining_time":0.8897525436},
{"learn":[14.61408645],"iteration":3,"passed_time":0.003517233608,"remaining_time":0.8757911683},
{"learn":[14.51957468],"iteration":4,"passed_time":0.004330670856,"remaining_time":0.8618035004},
{"learn":[14.42874012],"iteration":5,"passed_time":0.005138648501,"remaining_time":0.8513027683},
{"learn":[14.3415246],"iteration":6,"passed_time":0.005955651771,"remaining_time":0.8448517441},
{"learn":[14.25698782],"iteration":7,"passed_time":0.006790163143,"remaining_time":0.8419802297},
{"learn":[14.16444619],"iteration":8,"passed_time":0.007665672804,"remaining_time":0.8440757499},
{"learn":[14.06649289],"iteration":9,"passed_time":0.00843492479,"remaining_time":0.8350575542},
{"learn":[13.97154017],"iteration":10,"passed_time":0.009182608279,"remaining_time":0.8255999625},
{"learn":[13.88269899],"iteration":11,"passed_time":0.01004366619,"remaining_time":0.8269285165},
{"learn":[13.79656232],"iteration":12,"passed_time":0.01087084215,"remaining_time":0.8253477848},
{"learn":[13.70813938],"iteration":13,"passed_time":0.01166088676,"remaining_time":0.8212595963},
{"learn":[13.61892682],"iteration":14,"passed_time":0.01254970979,"remaining_time":0.8240976096},
{"learn":[13.52637441],"iteration":15,"passed_time":0.01346279929,"remaining_time":0.8279621562},
{"learn":[13.43624911],"iteration":16,"passed_time":0.01426094857,"remaining_time":0.8246183791},
{"learn":[13.35247178],"iteration":17,"passed_time":0.01576560696,"remaining_time":0.8601014465},
{"learn":[13.26556337],"iteration":18,"passed_time":0.0164526747,"remaining_time":0.8494775729},
{"learn":[13.18188505],"iteration":19,"passed_time":0.01717331893,"remaining_time":0.8414926277},
{"learn":[13.11347225],"iteration":20,"passed_time":0.01792988668,"remaining_time":0.8358742409},
{"learn":[13.04032099],"iteration":21,"passed_time":0.01870071934,"remaining_time":0.8313319778},
{"learn":[12.95319961],"iteration":22,"passed_time":0.01938302233,"remaining_time":0.8233570788},
{"learn":[12.8702586],"iteration":23,"passed_time":0.02012407021,"remaining_time":0.8183788554},
{"learn":[12.78891644],"iteration":24,"passed_time":0.02085548856,"remaining_time":0.8133640539},
{"learn":[12.71417622],"iteration":25,"passed_time":0.02160571998,"remaining_time":0.8093835099},
{"learn":[12.6351451],"iteration":26,"passed_time":0.0223722682,"remaining_time":0.8062302578},
{"learn":[12.55967174],"iteration":27,"passed_time":0.0230810797,"remaining_time":0.8012431954},
{"learn":[12.47873478],"iteration":28,"passed_time":0.02378671705,"remaining_time":0.7964449052},
{"learn":[12.4067952],"iteration":29,"passed_time":0.02446137833,"remaining_time":0.7909178992},
{"learn":[12.33389757],"iteration":30,"passed_time":0.02519339067,"remaining_time":0.7874966308},
{"learn":[12.25550289],"iteration":31,"passed_time":0.02606235897,"remaining_time":0.7883863589},
{"learn":[12.18194297],"iteration":32,"passed_time":0.02676681949,"remaining_time":0.7843489226},
{"learn":[12.11349676],"iteration":33,"passed_time":0.02744969787,"remaining_time":0.7798943571},
{"learn":[12.0368928],"iteration":34,"passed_time":0.02807161907,"remaining_time":0.7739746402},
{"learn":[11.96797082],"iteration":35,"passed_time":0.02873968898,"remaining_time":0.7695850049},
{"learn":[11.89589759],"iteration":36,"passed_time":0.02944904115,"remaining_time":0.76647099},
{"learn":[11.82381299],"iteration":37,"passed_time":0.03013449846,"remaining_time":0.7628786189},
{"learn":[11.75179457],"iteration":38,"passed_time":0.03082102099,"remaining_time":0.7594615684},
{"learn":[11.67841503],"iteration":39,"passed_time":0.03150144651,"remaining_time":0.7560347163},
{"learn":[11.60851553],"iteration":40,"passed_time":0.03217686795,"remaining_time":0.7526247895},
{"learn":[11.54731332],"iteration":41,"passed_time":0.03288979979,"remaining_time":0.7502006713},
{"learn":[11.47943531],"iteration":42,"passed_time":0.0335633107,"remaining_time":0.7469787985},
{"learn":[11.42226959],"iteration":43,"passed_time":0.03420853897,"remaining_time":0.7432582558},
{"learn":[11.35795462],"iteration":44,"passed_time":0.03490653626,"remaining_time":0.7407942695},
{"learn":[11.29088618],"iteration":45,"passed_time":0.03561926885,"remaining_time":0.7387126627},
{"learn":[11.22635734],"iteration":46,"passed_time":0.03631974834,"remaining_time":0.7364408547},
{"learn":[11.16618638],"iteration":47,"passed_time":0.03706778897,"remaining_time":0.7351778146},
{"learn":[11.10831098],"iteration":48,"passed_time":0.03776524269,"remaining_time":0.7329539959},
{"learn":[11.04838888],"iteration":49,"passed_time":0.03845871704,"remaining_time":0.7307156237},
{"learn":[10.98660201],"iteration":50,"passed_time":0.03911429492,"remaining_time":0.7278326642},
{"learn":[10.92429286],"iteration":51,"passed_time":0.03980506467,"remaining_time":0.7256769483},
{"learn":[10.86717729],"iteration":52,"passed_time":0.04054454512,"remaining_time":0.7244468722},
{"learn":[10.80371647],"iteration":53,"passed_time":0.04117593217,"remaining_time":0.7213413302},
{"learn":[10.74431286],"iteration":54,"passed_time":0.04185109361,"remaining_time":0.7190778811},
{"learn":[10.68427459],"iteration":55,"passed_time":0.04253088381,"remaining_time":0.7169491842},
{"learn":[10.62713108],"iteration":56,"passed_time":0.04318506702,"remaining_time":0.7144476878},
{"learn":[10.56832774],"iteration":57,"passed_time":0.04382645977,"remaining_time":0.7118021569},
{"learn":[10.5106423],"iteration":58,"passed_time":0.04449813786,"remaining_time":0.7097075885},
{"learn":[10.45953296],"iteration":59,"passed_time":0.04520332506,"remaining_time":0.7081854259},
{"learn":[10.40365151],"iteration":60,"passed_time":0.04589248603,"remaining_time":0.7064433506},
{"learn":[10.3475546],"iteration":61,"passed_time":0.04656557367,"remaining_time":0.7044920661},
{"learn":[10.29465126],"iteration":62,"passed_time":0.04726367016,"remaining_time":0.7029533165},
{"learn":[10.23774778],"iteration":63,"passed_time":0.04793048346,"remaining_time":0.7009833206},
{"learn":[10.18568485],"iteration":64,"passed_time":0.04862241392,"remaining_time":0.6994147234},
{"learn":[10.13038471],"iteration":65,"passed_time":0.04931203042,"remaining_time":0.6978399456},
{"learn":[10.0740356],"iteration":66,"passed_time":0.04997540212,"remaining_time":0.6959261221},
{"learn":[10.02227541],"iteration":67,"passed_time":0.05064360802,"remaining_time":0.6941153335},
{"learn":[9.970593295],"iteration":68,"passed_time":0.05137935049,"remaining_time":0.6932489174},
{"learn":[9.91947382],"iteration":69,"passed_time":0.05201484878,"remaining_time":0.6910544195},
{"learn":[9.866722467],"iteration":70,"passed_time":0.05266507783,"remaining_time":0.6890965817},
{"learn":[9.816754407],"iteration":71,"passed_time":0.05335918006,"remaining_time":0.687740543},
{"learn":[9.765537844],"iteration":72,"passed_time":0.05402613432,"remaining_time":0.6860578975},
{"learn":[9.718362816],"iteration":73,"passed_time":0.05483611426,"remaining_time":0.6861924569},
{"learn":[9.669391201],"iteration":74,"passed_time":0.05558094312,"remaining_time":0.6854982984},
{"learn":[9.621746972],"iteration":75,"passed_time":0.05629538204,"remaining_time":0.6844333291},
{"learn":[9.572537677],"iteration":76,"passed_time":0.05700139843,"remaining_time":0.6832765033},
{"learn":[9.526536128],"iteration":77,"passed_time":0.0577000327,"remaining_time":0.6820439763},
{"learn":[9.48371628],"iteration":78,"passed_time":0.05839441188,"remaining_time":0.6807753588},
{"learn":[9.445491082],"iteration":79,"passed_time":0.05884129506,"remaining_time":0.6766748932},
{"learn":[9.398569124],"iteration":80,"passed_time":0.05956839218,"remaining_time":0.675843857},
{"learn":[9.354063972],"iteration":81,"passed_time":0.06022295941,"remaining_time":0.6742033748},
{"learn":[9.307098902],"iteration":82,"passed_time":0.0608896826,"remaining_time":0.6727209511},
{"learn":[9.26842072],"iteration":83,"passed_time":0.06160764043,"remaining_time":0.6718166504},
{"learn":[9.221365976],"iteration":84,"passed_time":0.06228145226,"remaining_time":0.6704415155},
{"learn":[9.178536688],"iteration":85,"passed_time":0.0630440178,"remaining_time":0.6700259566},
{"learn":[9.138841687],"iteration":86,"passed_time":0.06372374186,"remaining_time":0.6687330612},
{"learn":[9.096537479],"iteration":87,"passed_time":0.06443288901,"remaining_time":0.6677590316},
{"learn":[9.056597471],"iteration":88,"passed_time":0.06511092658,"remaining_time":0.6664725182},
{"learn":[9.01490307],"iteration":89,"passed_time":0.0658616346,"remaining_time":0.6659343054},
{"learn":[8.977826531],"iteration":90,"passed_time":0.0665981893,"remaining_time":0.6652500448},
{"learn":[8.936753503],"iteration":91,"passed_time":0.06731755916,"remaining_time":0.6643950404},
{"learn":[8.895059295],"iteration":92,"passed_time":0.06803950918,"remaining_time":0.6635681164},
{"learn":[8.861743043],"iteration":93,"passed_time":0.06869118291,"remaining_time":0.6620660821},
{"learn":[8.825223339],"iteration":94,"passed_time":0.069395977,"remaining_time":0.6610879915},
{"learn":[8.786465359],"iteration":95,"passed_time":0.07014246135,"remaining_time":0.6605081777},
{"learn":[8.746461018],"iteration":96,"passed_time":0.07085804569,"remaining_time":0.6596372707},
{"learn":[8.708916962],"iteration":97,"passed_time":0.07149331208,"remaining_time":0.6580302806},
{"learn":[8.670256098],"iteration":98,"passed_time":0.07219453644,"remaining_time":0.6570432054},
{"learn":[8.632172304],"iteration":99,"passed_time":0.07286916134,"remaining_time":0.6558224521},
{"learn":[8.593616929],"iteration":100,"passed_time":0.07352596441,"remaining_time":0.6544538812},
{"learn":[8.558341384],"iteration":101,"passed_time":0.07420270115,"remaining_time":0.6532747611},
{"learn":[8.52696993],"iteration":102,"passed_time":0.07492497813,"remaining_time":0.652501994},
{"learn":[8.489976409],"iteration":103,"passed_time":0.07558018192,"remaining_time":0.6511523366},
{"learn":[8.454174938],"iteration":104,"passed_time":0.07622866785,"remaining_time":0.649758645},
{"learn":[8.416924581],"iteration":105,"passed_time":0.07689328789,"remaining_time":0.6485150884},
{"learn":[8.381466861],"iteration":106,"passed_time":0.07762937468,"remaining_time":0.6478787999},
{"learn":[8.346847622],"iteration":107,"passed_time":0.0783283417,"remaining_time":0.6469340814},
{"learn":[8.314175576],"iteration":108,"passed_time":0.0789865076,"remaining_time":0.6456603511},
{"learn":[8.281770212],"iteration":109,"passed_time":0.07968035024,"remaining_time":0.6446864702},
{"learn":[8.246489425],"iteration":110,"passed_time":0.08039199654,"remaining_time":0.6438602246},
{"learn":[8.210759934],"iteration":111,"passed_time":0.08105540834,"remaining_time":0.6426535947},
{"learn":[8.178253689],"iteration":112,"passed_time":0.08168356543,"remaining_time":0.6411798455},
{"learn":[8.14935928],"iteration":113,"passed_time":0.08235353967,"remaining_time":0.6400459311},
{"learn":[8.119869733],"iteration":114,"passed_time":0.08297551461,"remaining_time":0.6385506994},
{"learn":[8.092463517],"iteration":115,"passed_time":0.08387038875,"remaining_time":0.6391502039},
{"learn":[8.06164814],"iteration":116,"passed_time":0.08461050617,"remaining_time":0.6385562133},
{"learn":[8.032883057],"iteration":117,"passed_time":0.08542086433,"remaining_time":0.6384847656},
{"learn":[8.002632059],"iteration":118,"passed_time":0.08611648937,"remaining_time":0.6375514885},
{"learn":[7.969752901],"iteration":119,"passed_time":0.08684759977,"remaining_time":0.6368823983},
{"learn":[7.941336118],"iteration":120,"passed_time":0.08754933048,"remaining_time":0.6359988553},
{"learn":[7.911495732],"iteration":121,"passed_time":0.08826747391,"remaining_time":0.6352364106},
{"learn":[7.880662265],"iteration":122,"passed_time":0.08894784198,"remaining_time":0.6342053448},
{"learn":[7.851937576],"iteration":123,"passed_time":0.08965339665,"remaining_time":0.6333578667},
{"learn":[7.822725057],"iteration":124,"passed_time":0.09036421706,"remaining_time":0.6325495194},
{"learn":[7.796863107],"iteration":125,"passed_time":0.09111573319,"remaining_time":0.6320250064},
{"learn":[7.768178982],"iteration":126,"passed_time":0.09180098464,"remaining_time":0.6310414141},
{"learn":[7.739953674],"iteration":127,"passed_time":0.09259644629,"remaining_time":0.6308132903},
{"learn":[7.71516065],"iteration":128,"passed_time":0.09333549518,"remaining_time":0.6301954752},
{"learn":[7.68924738],"iteration":129,"passed_time":0.09397676847,"remaining_time":0.6289214505},
{"learn":[7.662309868],"iteration":130,"passed_time":0.0946388782,"remaining_time":0.6277953065},
{"learn":[7.638542915],"iteration":131,"passed_time":0.09538466232,"remaining_time":0.6272264158},
{"learn":[7.611173706],"iteration":132,"passed_time":0.09610513004,"remaining_time":0.6264898327},
{"learn":[7.588056015],"iteration":133,"passed_time":0.09680263295,"remaining_time":0.6256050757},
{"learn":[7.563073006],"iteration":134,"passed_time":0.09756983759,"remaining_time":0.6251697001},
{"learn":[7.540696684],"iteration":135,"passed_time":0.09807522674,"remaining_time":0.6230661463},
{"learn":[7.515166524],"iteration":136,"passed_time":0.09881137471,"remaining_time":0.6224395356},
{"learn":[7.489213865],"iteration":137,"passed_time":0.09953387738,"remaining_time":0.6217261036},
{"learn":[7.4671567],"iteration":138,"passed_time":0.1002545158,"remaining_time":0.6210009937},
{"learn":[7.443278731],"iteration":139,"passed_time":0.1009484874,"remaining_time":0.6201121371},
{"learn":[7.419159194],"iteration":140,"passed_time":0.1015948524,"remaining_time":0.6189360159},
{"learn":[7.395963061],"iteration":141,"passed_time":0.1023571861,"remaining_time":0.618468068},
{"learn":[7.374921554],"iteration":142,"passed_time":0.1031423572,"remaining_time":0.6181328682},
{"learn":[7.35329762],"iteration":143,"passed_time":0.103961474,"remaining_time":0.6179932065},
{"learn":[7.329195984],"iteration":144,"passed_time":0.1047036619,"remaining_time":0.6173905582},
{"learn":[7.306648601],"iteration":145,"passed_time":0.10553806,"remaining_time":0.6173253648},
{"learn":[7.284603988],"iteration":146,"passed_time":0.1062988787,"remaining_time":0.6168227453},
{"learn":[7.262922602],"iteration":147,"passed_time":0.1070113245,"remaining_time":0.6160381651},
{"learn":[7.240410944],"iteration":148,"passed_time":0.1078172275,"remaining_time":0.615788326},
{"learn":[7.219014548],"iteration":149,"passed_time":0.1085393527,"remaining_time":0.6150563322},
{"learn":[7.199098585],"iteration":150,"passed_time":0.1092262585,"remaining_time":0.6141264465},
{"learn":[7.179469951],"iteration":151,"passed_time":0.1099044494,"remaining_time":0.6131511386},
{"learn":[7.157723805],"iteration":152,"passed_time":0.1106175904,"remaining_time":0.6123731964},
{"learn":[7.135543815],"iteration":153,"passed_time":0.1113154996,"remaining_time":0.6115124199},
{"learn":[7.113130086],"iteration":154,"passed_time":0.1119603989,"remaining_time":0.610364755},
{"learn":[7.092866641],"iteration":155,"passed_time":0.1126657675,"remaining_time":0.6095506909},
{"learn":[7.070706823],"iteration":156,"passed_time":0.1133559131,"remaining_time":0.6086562723},
{"learn":[7.049542242],"iteration":157,"passed_time":0.114027697,"remaining_time":0.6076665879},
{"learn":[7.029749195],"iteration":158,"passed_time":0.1147084751,"remaining_time":0.6067284754},
{"learn":[7.012748292],"iteration":159,"passed_time":0.1151413724,"remaining_time":0.6044922052},
{"learn":[6.992498653],"iteration":160,"passed_time":0.115863959,"remaining_time":0.6037879603},
{"learn":[6.971514968],"iteration":161,"passed_time":0.1165409268,"remaining_time":0.6028475103},
{"learn":[6.95112065],"iteration":162,"passed_time":0.1172469333,"remaining_time":0.6020594058},
{"learn":[6.936804145],"iteration":163,"passed_time":0.1180036585,"remaining_time":0.6015308446},
{"learn":[6.918483741],"iteration":164,"passed_time":0.1186802187,"remaining_time":0.6005938343},
{"learn":[6.899104772],"iteration":165,"passed_time":0.1193598494,"remaining_time":0.5996753879},
{"learn":[6.88109537],"iteration":166,"passed_time":0.1200510416,"remaining_time":0.598817471},
{"learn":[6.862065294],"iteration":167,"passed_time":0.120700279,"remaining_time":0.5977537627},
{"learn":[6.846172347],"iteration":168,"passed_time":0.1213372765,"remaining_time":0.596634774},
{"learn":[6.827825318],"iteration":169,"passed_time":0.1221048751,"remaining_time":0.5961590961},
{"learn":[6.812280268],"iteration":170,"passed_time":0.122823701,"remaining_time":0.5954435562},
{"learn":[6.798641759],"iteration":171,"passed_time":0.1235161977,"remaining_time":0.594601231},
{"learn":[6.781204229],"iteration":172,"passed_time":0.1241745021,"remaining_time":0.5935971864},
{"learn":[6.764758805],"iteration":173,"passed_time":0.1248481176,"remaining_time":0.5926697996},
{"learn":[6.747624968],"iteration":174,"passed_time":0.1255079266,"remaining_time":0.5916802254},
{"learn":[6.731155847],"iteration":175,"passed_time":0.1261400056,"remaining_time":0.5905645717},
{"learn":[6.714120881],"iteration":176,"passed_time":0.1267523646,"remaining_time":0.5893626898},
{"learn":[6.69760595],"iteration":177,"passed_time":0.1274225228,"remaining_time":0.588434347},
{"learn":[6.681652804],"iteration":178,"passed_time":0.128056397,"remaining_time":0.5873424691},
{"learn":[6.668827838],"iteration":179,"passed_time":0.1287184431,"remaining_time":0.5863840186},
{"learn":[6.651982117],"iteration":180,"passed_time":0.1293369979,"remaining_time":0.5852320515},
{"learn":[6.638450641],"iteration":181,"passed_time":0.1300201855,"remaining_time":0.5843764382},
{"learn":[6.623279337],"iteration":182,"passed_time":0.1306875635,"remaining_time":0.5834521276},
{"learn":[6.607003516],"iteration":183,"passed_time":0.1313261999,"remaining_time":0.5824031476},
{"learn":[6.59177276],"iteration":184,"passed_time":0.1319691721,"remaining_time":0.5813777042},
{"learn":[6.577733275],"iteration":185,"passed_time":0.1325730305,"remaining_time":0.580185198},
{"learn":[6.563451067],"iteration":186,"passed_time":0.1332118712,"remaining_time":0.5791510763},
{"learn":[6.54858762],"iteration":187,"passed_time":0.1338457078,"remaining_time":0.5780995464},
{"learn":[6.535014777],"iteration":188,"passed_time":0.1345071437,"remaining_time":0.5771708655},
{"learn":[6.520930744],"iteration":189,"passed_time":0.1351657767,"remaining_time":0.5762330482},
{"learn":[6.508453126],"iteration":190,"passed_time":0.1358393447,"remaining_time":0.5753614129},
{"learn":[6.493562788],"iteration":191,"passed_time":0.136514583,"remaining_time":0.5744988702},
{"learn":[6.480684901],"iteration":192,"passed_time":0.1371381634,"remaining_time":0.5734222688},
{"learn":[6.468692901],"iteration":193,"passed_time":0.1378157938,"remaining_time":0.5725748961},
{"learn":[6.454229284],"iteration":194,"passed_time":0.1384654343,"remaining_time":0.5716137159},
{"learn":[6.44130333],"iteration":195,"passed_time":0.1391410314,"remaining_time":0.57076219},
{"learn":[6.429857027],"iteration":196,"passed_time":0.13978507,"remaining_time":0.5697838134},
{"learn":[6.417005814],"iteration":197,"passed_time":0.1404306335,"remaining_time":0.5688149904},
{"learn":[6.403780912],"iteration":198,"passed_time":0.1410813206,"remaining_time":0.5678700391},
{"learn":[6.39190858],"iteration":199,"passed_time":0.1417307812,"remaining_time":0.5669231248},
{"learn":[6.378189291],"iteration":200,"passed_time":0.1423529215,"remaining_time":0.5658705685},
{"learn":[6.36444611],"iteration":201,"passed_time":0.1430421858,"remaining_time":0.5650874469},
{"learn":[6.352767956],"iteration":202,"passed_time":0.1436518349,"remaining_time":0.563992672},
{"learn":[6.342224184],"iteration":203,"passed_time":0.1442509529,"remaining_time":0.5628615613},
{"learn":[6.330822459],"iteration":204,"passed_time":0.1449162211,"remaining_time":0.5619921744},
{"learn":[6.320152049],"iteration":205,"passed_time":0.1455417914,"remaining_time":0.560971759},
{"learn":[6.308428586],"iteration":206,"passed_time":0.1461891005,"remaining_time":0.5600384381},
{"learn":[6.297540356],"iteration":207,"passed_time":0.146809329,"remaining_time":0.5590047528},
{"learn":[6.28629099],"iteration":208,"passed_time":0.1474534024,"remaining_time":0.5580652692},
{"learn":[6.275841374],"iteration":209,"passed_time":0.1481193588,"remaining_time":0.5572109211},
{"learn":[6.264483662],"iteration":210,"passed_time":0.1488249006,"remaining_time":0.556506382},
{"learn":[6.254533821],"iteration":211,"passed_time":0.1495461343,"remaining_time":0.5558601596},
{"learn":[6.24339262],"iteration":212,"passed_time":0.1502739308,"remaining_time":0.5552374815},
{"learn":[6.231009598],"iteration":213,"passed_time":0.1510074639,"remaining_time":0.5546348908},
{"learn":[6.219930013],"iteration":214,"passed_time":0.1517022581,"remaining_time":0.5538896401},
{"learn":[6.208063951],"iteration":215,"passed_time":0.1523946714,"remaining_time":0.5531362146},
{"learn":[6.19741683],"iteration":216,"passed_time":0.1530480332,"remaining_time":0.5522424425},
{"learn":[6.187050261],"iteration":217,"passed_time":0.1536941511,"remaining_time":0.5513248905},
{"learn":[6.17531516],"iteration":218,"passed_time":0.1544088595,"remaining_time":0.5506544259},
{"learn":[6.164888099],"iteration":219,"passed_time":0.1551071928,"remaining_time":0.5499255019},
{"learn":[6.154696147],"iteration":220,"passed_time":0.1558280305,"remaining_time":0.54927618},
{"learn":[6.14426803],"iteration":221,"passed_time":0.156506522,"remaining_time":0.5484778112},
{"learn":[6.135221696],"iteration":222,"passed_time":0.1572170336,"remaining_time":0.5477920856},
{"learn":[6.124868134],"iteration":223,"passed_time":0.1579334079,"remaining_time":0.5471264486},
{"learn":[6.114203388],"iteration":224,"passed_time":0.1585700032,"remaining_time":0.5461855665},
{"learn":[6.103976895],"iteration":225,"passed_time":0.1592121317,"remaining_time":0.5452663272},
{"learn":[6.094238906],"iteration":226,"passed_time":0.1599096144,"remaining_time":0.544538026},
{"learn":[6.083259792],"iteration":227,"passed_time":0.1605574431,"remaining_time":0.5436418686},
{"learn":[6.073858783],"iteration":228,"passed_time":0.1612599339,"remaining_time":0.5429319173},
{"learn":[6.064932703],"iteration":229,"passed_time":0.1619096265,"remaining_time":0.5420452712},
{"learn":[6.054209735],"iteration":230,"passed_time":0.1626741186,"remaining_time":0.5415428452},
{"learn":[6.047095961],"iteration":231,"passed_time":0.1634147238,"remaining_time":0.5409590858},
{"learn":[6.041890794],"iteration":232,"passed_time":0.163840721,"remaining_time":0.539338339},
{"learn":[6.032632521],"iteration":233,"passed_time":0.1645372727,"remaining_time":0.5386134655},
{"learn":[6.022967446],"iteration":234,"passed_time":0.1651952262,"remaining_time":0.5377631831},
{"learn":[6.013867551],"iteration":235,"passed_time":0.1658991117,"remaining_time":0.5370632261},
{"learn":[6.007333054],"iteration":236,"passed_time":0.1665863601,"remaining_time":0.5363096741},
{"learn":[5.998811077],"iteration":237,"passed_time":0.1672548467,"remaining_time":0.5354966099},
{"learn":[5.990632728],"iteration":238,"passed_time":0.1679130444,"remaining_time":0.5346519949},
{"learn":[5.98399256],"iteration":239,"passed_time":0.1685504755,"remaining_time":0.5337431725},
{"learn":[5.975442939],"iteration":240,"passed_time":0.1692566234,"remaining_time":0.5330530172},
{"learn":[5.96774489],"iteration":241,"passed_time":0.1700118651,"remaining_time":0.532516503},
{"learn":[5.960078847],"iteration":242,"passed_time":0.1707045561,"remaining_time":0.5317833291},
{"learn":[5.951180473],"iteration":243,"passed_time":0.1713288136,"remaining_time":0.5308384552},
{"learn":[5.942486976],"iteration":244,"passed_time":0.1720029578,"remaining_time":0.5300499311},
{"learn":[5.934655867],"iteration":245,"passed_time":0.1727021253,"remaining_time":0.5293390343},
{"learn":[5.926786537],"iteration":246,"passed_time":0.1733615102,"remaining_time":0.528506952},
{"learn":[5.920856272],"iteration":247,"passed_time":0.1738486253,"remaining_time":0.5271538959},
{"learn":[5.913828545],"iteration":248,"passed_time":0.1744653287,"remaining_time":0.5261986419},
{"learn":[5.905224118],"iteration":249,"passed_time":0.1751663844,"remaining_time":0.5254991531},
{"learn":[5.897022748],"iteration":250,"passed_time":0.1758404574,"remaining_time":0.524719134},
{"learn":[5.890220444],"iteration":251,"passed_time":0.1765040197,"remaining_time":0.5239087569},
{"learn":[5.88123931],"iteration":252,"passed_time":0.1771653031,"remaining_time":0.523092812},
{"learn":[5.872794425],"iteration":253,"passed_time":0.1777702714,"remaining_time":0.5221126868},
{"learn":[5.864265149],"iteration":254,"passed_time":0.1784558233,"remaining_time":0.5213709349},
{"learn":[5.85663108],"iteration":255,"passed_time":0.1790819438,"remaining_time":0.5204568992},
{"learn":[5.851049231],"iteration":256,"passed_time":0.1797454313,"remaining_time":0.519653134},
{"learn":[5.843850613],"iteration":257,"passed_time":0.180418659,"remaining_time":0.518878469},
{"learn":[5.836945762],"iteration":258,"passed_time":0.1810356836,"remaining_time":0.5179437898},
{"learn":[5.830696806],"iteration":259,"passed_time":0.1816864604,"remaining_time":0.517107618},
{"learn":[5.82359864],"iteration":260,"passed_time":0.1822934487,"remaining_time":0.5161488834},
{"learn":[5.816610492],"iteration":261,"passed_time":0.1830095348,"remaining_time":0.5155001401},
{"learn":[5.811063116],"iteration":262,"passed_time":0.1837401194,"remaining_time":0.5148915134},
{"learn":[5.805268822],"iteration":263,"passed_time":0.1841796242,"remaining_time":0.5134704675},
{"learn":[5.799755793],"iteration":264,"passed_time":0.1849209619,"remaining_time":0.5128939886},
{"learn":[5.793009059],"iteration":265,"passed_time":0.1855686153,"remaining_time":0.512057758},
{"learn":[5.786520923],"iteration":266,"passed_time":0.18609365,"remaining_time":0.5108863126},
{"learn":[5.780041243],"iteration":267,"passed_time":0.1867803949,"remaining_time":0.5101613772},
{"learn":[5.774018181],"iteration":268,"passed_time":0.1874432979,"remaining_time":0.5093719359},
{"learn":[5.768033121],"iteration":269,"passed_time":0.1881980216,"remaining_time":0.5088316882},
{"learn":[5.761761228],"iteration":270,"passed_time":0.1889868386,"remaining_time":0.5083815695},
{"learn":[5.755610341],"iteration":271,"passed_time":0.1897037424,"remaining_time":0.5077364869},
{"learn":[5.751312104],"iteration":272,"passed_time":0.1901258754,"remaining_time":0.5063059027},
{"learn":[5.74544464],"iteration":273,"passed_time":0.1907788029,"remaining_time":0.5054942003},
{"learn":[5.738636421],"iteration":274,"passed_time":0.1913853968,"remaining_time":0.5045615008},
{"learn":[5.732319318],"iteration":275,"passed_time":0.1920549871,"remaining_time":0.5037964154},
{"learn":[5.725791067],"iteration":276,"passed_time":0.1927445664,"remaining_time":0.5030841931},
{"learn":[5.720502377],"iteration":277,"passed_time":0.1934146989,"remaining_time":0.5023216281},
{"learn":[5.714925193],"iteration":278,"passed_time":0.1940658444,"remaining_time":0.5015106588},
{"learn":[5.709349888],"iteration":279,"passed_time":0.194690905,"remaining_time":0.5006337558},
{"learn":[5.703002576],"iteration":280,"passed_time":0.1953054648,"remaining_time":0.4997317764},
{"learn":[5.698065484],"iteration":281,"passed_time":0.1959163647,"remaining_time":0.4988225171},
{"learn":[5.691878337],"iteration":282,"passed_time":0.1965916286,"remaining_time":0.4980784372},
{"learn":[5.687011086],"iteration":283,"passed_time":0.1973026016,"remaining_time":0.4974248687},
{"learn":[5.681701709],"iteration":284,"passed_time":0.1979508077,"remaining_time":0.4966134297},
{"learn":[5.675228111],"iteration":285,"passed_time":0.1986288684,"remaining_time":0.4958776644},
{"learn":[5.67006498],"iteration":286,"passed_time":0.1992206741,"remaining_time":0.4949280162},
{"learn":[5.66474822],"iteration":287,"passed_time":0.1998518669,"remaining_time":0.4940782265},
{"learn":[5.659473913],"iteration":288,"passed_time":0.2004806085,"remaining_time":0.4932239191},
{"learn":[5.653253822],"iteration":289,"passed_time":0.2011625837,"remaining_time":0.4925014979},
{"learn":[5.647752652],"iteration":290,"passed_time":0.2018294524,"remaining_time":0.4917425489},
{"learn":[5.643004391],"iteration":291,"passed_time":0.2023366065,"remaining_time":0.4905969775},
{"learn":[5.638118758],"iteration":292,"passed_time":0.202961482,"remaining_time":0.4897398218},
{"learn":[5.633367751],"iteration":293,"passed_time":0.2036373032,"remaining_time":0.4890065851},
{"learn":[5.627354584],"iteration":294,"passed_time":0.2042302403,"remaining_time":0.4880756589},
{"learn":[5.622599176],"iteration":295,"passed_time":0.204846508,"remaining_time":0.4872025055},
{"learn":[5.617105405],"iteration":296,"passed_time":0.2055359806,"remaining_time":0.4865043582},
{"learn":[5.612845184],"iteration":297,"passed_time":0.206209747,"remaining_time":0.4857692698},
{"learn":[5.608179933],"iteration":298,"passed_time":0.2068288363,"remaining_time":0.4849064022},
{"learn":[5.603992679],"iteration":299,"passed_time":0.2075503205,"remaining_time":0.4842840811},
{"learn":[5.598958874],"iteration":300,"passed_time":0.2082734068,"remaining_time":0.4836648218},
{"learn":[5.59389345],"iteration":301,"passed_time":0.2089270882,"remaining_time":0.4828844621},
{"learn":[5.588342081],"iteration":302,"passed_time":0.2095778493,"remaining_time":0.4820982209},
{"learn":[5.58330983],"iteration":303,"passed_time":0.2102173517,"remaining_time":0.4812870947},
{"learn":[5.578551572],"iteration":304,"passed_time":0.2108561639,"remaining_time":0.480475521},
{"learn":[5.574623415],"iteration":305,"passed_time":0.2114861641,"remaining_time":0.4796450912},
{"learn":[5.569803613],"iteration":306,"passed_time":0.2122213213,"remaining_time":0.4790533409},
{"learn":[5.565021478],"iteration":307,"passed_time":0.2130339297,"remaining_time":0.4786346733},
{"learn":[5.561025858],"iteration":308,"passed_time":0.2137423081,"remaining_time":0.4779803717},
{"learn":[5.556691574],"iteration":309,"passed_time":0.2144204853,"remaining_time":0.4772584996},
{"learn":[5.55170604],"iteration":310,"passed_time":0.2151664005,"remaining_time":0.4766869773},
{"learn":[5.547294577],"iteration":311,"passed_time":0.2158183152,"remaining_time":0.4759070541},
{"learn":[5.541753683],"iteration":312,"passed_time":0.2164782168,"remaining_time":0.475145479},
{"learn":[5.53721509],"iteration":313,"passed_time":0.217151743,"remaining_time":0.4744143175},
{"learn":[5.532844808],"iteration":314,"passed_time":0.2178467604,"remaining_time":0.4737302567},
{"learn":[5.528969498],"iteration":315,"passed_time":0.2186103039,"remaining_time":0.4731944554},
{"learn":[5.524587779],"iteration":316,"passed_time":0.2192795573,"remaining_time":0.4724540619},
{"learn":[5.520880304],"iteration":317,"passed_time":0.2199731403,"remaining_time":0.4717662947},
{"learn":[5.517133278],"iteration":318,"passed_time":0.220705843,"remaining_time":0.4711620034},
{"learn":[5.513136261],"iteration":319,"passed_time":0.2215570395,"remaining_time":0.4708087089},
{"learn":[5.509393446],"iteration":320,"passed_time":0.2222952112,"remaining_time":0.470213235},
{"learn":[5.505077898],"iteration":321,"passed_time":0.2230654718,"remaining_time":0.4696844406},
{"learn":[5.501490298],"iteration":322,"passed_time":0.2238369534,"remaining_time":0.4691567104},
{"learn":[5.496886789],"iteration":323,"passed_time":0.2245510327,"remaining_time":0.4685077103},
{"learn":[5.493773807],"iteration":324,"passed_time":0.2252958141,"remaining_time":0.4679220753},
{"learn":[5.490701805],"iteration":325,"passed_time":0.2259750206,"remaining_time":0.4671998892},
{"learn":[5.486140036],"iteration":326,"passed_time":0.2266522145,"remaining_time":0.4664738237},
{"learn":[5.482057338],"iteration":327,"passed_time":0.2273196834,"remaining_time":0.4657281318},
{"learn":[5.478002124],"iteration":328,"passed_time":0.2280123666,"remaining_time":0.4650343403},
{"learn":[5.47694727],"iteration":329,"passed_time":0.2284035988,"remaining_time":0.4637285188},
{"learn":[5.472941813],"iteration":330,"passed_time":0.2290952623,"remaining_time":0.4630354394},
{"learn":[5.469076828],"iteration":331,"passed_time":0.2297998406,"remaining_time":0.4623683539},
{"learn":[5.465955128],"iteration":332,"passed_time":0.2304612352,"remaining_time":0.4616145462},
{"learn":[5.462792484],"iteration":333,"passed_time":0.2311331167,"remaining_time":0.4608822027},
{"learn":[5.459473445],"iteration":334,"passed_time":0.2317875487,"remaining_time":0.4601155818},
{"learn":[5.456847362],"iteration":335,"passed_time":0.2324879216,"remaining_time":0.4594404164},
{"learn":[5.45368045],"iteration":336,"passed_time":0.2332006095,"remaining_time":0.4587893297},
{"learn":[5.449417302],"iteration":337,"passed_time":0.2339203493,"remaining_time":0.4581516901},
{"learn":[5.446103289],"iteration":338,"passed_time":0.2346336867,"remaining_time":0.4575010822},
{"learn":[5.442247687],"iteration":339,"passed_time":0.2353931586,"remaining_time":0.4569396609},
{"learn":[5.43871318],"iteration":340,"passed_time":0.2360820766,"remaining_time":0.4562407286},
{"learn":[5.434387794],"iteration":341,"passed_time":0.2367311672,"remaining_time":0.4554652282},
{"learn":[5.430331476],"iteration":342,"passed_time":0.2373994017,"remaining_time":0.4547271338},
{"learn":[5.427309078],"iteration":343,"passed_time":0.2380666337,"remaining_time":0.453987534},
{"learn":[5.423101806],"iteration":344,"passed_time":0.2387555066,"remaining_time":0.45328944},
{"learn":[5.420860485],"iteration":345,"passed_time":0.2394101002,"remaining_time":0.4525266057},
{"learn":[5.417915372],"iteration":346,"passed_time":0.2400708256,"remaining_time":0.4517759341},
{"learn":[5.414995311],"iteration":347,"passed_time":0.2408025792,"remaining_time":0.4511588553},
{"learn":[5.411536052],"iteration":348,"passed_time":0.2415148013,"remaining_time":0.4505046867},
{"learn":[5.408800441],"iteration":349,"passed_time":0.2421812099,"remaining_time":0.4497651042},
{"learn":[5.405299329],"iteration":350,"passed_time":0.2428021407,"remaining_time":0.44894185},
{"learn":[5.402158131],"iteration":351,"passed_time":0.2435338315,"remaining_time":0.4483236444},
{"learn":[5.39950541],"iteration":352,"passed_time":0.2442691027,"remaining_time":0.4477113583},
{"learn":[5.396513947],"iteration":353,"passed_time":0.2449860305,"remaining_time":0.4470649031},
{"learn":[5.393482425],"iteration":354,"passed_time":0.2456424789,"remaining_time":0.4463081659},
{"learn":[5.390112004],"iteration":355,"passed_time":0.246332164,"remaining_time":0.4456121169},
{"learn":[5.386559945],"iteration":356,"passed_time":0.2470934093,"remaining_time":0.4450449921},
{"learn":[5.382728426],"iteration":357,"passed_time":0.2477734508,"remaining_time":0.4443311604},
{"learn":[5.380333419],"iteration":358,"passed_time":0.2485932707,"remaining_time":0.4438670933},
{"learn":[5.377356268],"iteration":359,"passed_time":0.2492531289,"remaining_time":0.4431166735},
{"learn":[5.37377165],"iteration":360,"passed_time":0.2499342244,"remaining_time":0.4424043474},
{"learn":[5.371265297],"iteration":361,"passed_time":0.250681173,"remaining_time":0.4418082551},
{"learn":[5.368459575],"iteration":362,"passed_time":0.2513466516,"remaining_time":0.4410683665},
{"learn":[5.364901372],"iteration":363,"passed_time":0.2519935258,"remaining_time":0.4402963803},
{"learn":[5.361414721],"iteration":364,"passed_time":0.2526492314,"remaining_time":0.4395404437},
{"learn":[5.358858927],"iteration":365,"passed_time":0.2533893488,"remaining_time":0.4389312764},
{"learn":[5.356914151],"iteration":366,"passed_time":0.2539220621,"remaining_time":0.4379636656},
{"learn":[5.354301564],"iteration":367,"passed_time":0.2545927588,"remaining_time":0.4372353902},
{"learn":[5.352021742],"iteration":368,"passed_time":0.255195087,"remaining_time":0.4363905146},
{"learn":[5.348774042],"iteration":369,"passed_time":0.2558606176,"remaining_time":0.4356545652},
{"learn":[5.34568617],"iteration":370,"passed_time":0.2564690787,"remaining_time":0.4348222386},
{"learn":[5.342407664],"iteration":371,"passed_time":0.2570570159,"remaining_time":0.4339564677},
{"learn":[5.339557569],"iteration":372,"passed_time":0.257700926,"remaining_time":0.433186275},
{"learn":[5.337039354],"iteration":373,"passed_time":0.2583981337,"remaining_time":0.4325059672},
{"learn":[5.334176686],"iteration":374,"passed_time":0.259009483,"remaining_time":0.4316824716},
{"learn":[5.330852676],"iteration":375,"passed_time":0.2596105603,"remaining_time":0.4308430575},
{"learn":[5.327342046],"iteration":376,"passed_time":0.260227794,"remaining_time":0.4300316066},
{"learn":[5.32513323],"iteration":377,"passed_time":0.2608516472,"remaining_time":0.4292320756},
{"learn":[5.323215417],"iteration":378,"passed_time":0.2614795402,"remaining_time":0.4284400909},
{"learn":[5.321696418],"iteration":379,"passed_time":0.2619127587,"remaining_time":0.4273313431},
{"learn":[5.318150482],"iteration":380,"passed_time":0.2625509272,"remaining_time":0.426559118},
{"learn":[5.315358687],"iteration":381,"passed_time":0.2632107499,"remaining_time":0.4258226267},
{"learn":[5.312063186],"iteration":382,"passed_time":0.2638400577,"remaining_time":0.4250373776},
{"learn":[5.309488939],"iteration":383,"passed_time":0.2644342766,"remaining_time":0.4241966521},
{"learn":[5.307588217],"iteration":384,"passed_time":0.2650643881,"remaining_time":0.423414542},
{"learn":[5.30543068],"iteration":385,"passed_time":0.2656970859,"remaining_time":0.4226373335},
{"learn":[5.301999181],"iteration":386,"passed_time":0.2663794625,"remaining_time":0.421939562},
{"learn":[5.299100812],"iteration":387,"passed_time":0.2671188619,"remaining_time":0.4213318131},
{"learn":[5.297070815],"iteration":388,"passed_time":0.2677136082,"remaining_time":0.4204961816},
{"learn":[5.295231189],"iteration":389,"passed_time":0.2683082723,"remaining_time":0.4196616567},
{"learn":[5.291961104],"iteration":390,"passed_time":0.2689499606,"remaining_time":0.4189016011},
{"learn":[5.289524257],"iteration":391,"passed_time":0.269617551,"remaining_time":0.4181823241},
{"learn":[5.286355802],"iteration":392,"passed_time":0.270221056,"remaining_time":0.4173643282},
{"learn":[5.284500396],"iteration":393,"passed_time":0.2708322667,"remaining_time":0.4165592732},
{"learn":[5.282098823],"iteration":394,"passed_time":0.2714616126,"remaining_time":0.4157829763},
{"learn":[5.27911827],"iteration":395,"passed_time":0.2721015971,"remaining_time":0.4150236481},
{"learn":[5.2769638],"iteration":396,"passed_time":0.272737584,"remaining_time":0.4142588492},
{"learn":[5.274568862],"iteration":397,"passed_time":0.2733245448,"remaining_time":0.4134205426},
{"learn":[5.273712133],"iteration":398,"passed_time":0.2736875663,"remaining_time":0.4122461838},
{"learn":[5.271396109],"iteration":399,"passed_time":0.2743498459,"remaining_time":0.4115247689},
{"learn":[5.268675951],"iteration":400,"passed_time":0.2749988308,"remaining_time":0.4107837896},
{"learn":[5.266643679],"iteration":401,"passed_time":0.2756954681,"remaining_time":0.4101141541},
{"learn":[5.264157326],"iteration":402,"passed_time":0.2763386561,"remaining_time":0.4093652051},
{"learn":[5.262437225],"iteration":403,"passed_time":0.2769736273,"remaining_time":0.4086046581},
{"learn":[5.259193851],"iteration":404,"passed_time":0.2776198167,"remaining_time":0.4078612121},
{"learn":[5.257394399],"iteration":405,"passed_time":0.2781623888,"remaining_time":0.4069666477},
{"learn":[5.254707957],"iteration":406,"passed_time":0.2788710598,"remaining_time":0.4063158193},
{"learn":[5.252925611],"iteration":407,"passed_time":0.2795819467,"remaining_time":0.4056679227},
{"learn":[5.250882902],"iteration":408,"passed_time":0.2802042668,"remaining_time":0.4048917401},
{"learn":[5.24927175],"iteration":409,"passed_time":0.2808972249,"remaining_time":0.4042179578},
{"learn":[5.246997374],"iteration":410,"passed_time":0.2816574285,"remaining_time":0.4036404511},
{"learn":[5.245226985],"iteration":411,"passed_time":0.2823734266,"remaining_time":0.4029989681},
{"learn":[5.243254323],"iteration":412,"passed_time":0.2831089988,"remaining_time":0.402384945},
{"learn":[5.241206261],"iteration":413,"passed_time":0.2839076594,"remaining_time":0.4018596338},
{"learn":[5.239222073],"iteration":414,"passed_time":0.284636288,"remaining_time":0.4012342855},
{"learn":[5.237277871],"iteration":415,"passed_time":0.2852617682,"remaining_time":0.4004636361},
{"learn":[5.234772222],"iteration":416,"passed_time":0.2859111118,"remaining_time":0.3997270461},
{"learn":[5.233338696],"iteration":417,"passed_time":0.2865404689,"remaining_time":0.3989630452},
{"learn":[5.232125823],"iteration":418,"passed_time":0.2872271084,"remaining_time":0.3982791169},
{"learn":[5.230086939],"iteration":419,"passed_time":0.287966662,"remaining_time":0.3976682476},
{"learn":[5.228344482],"iteration":420,"passed_time":0.2886216298,"remaining_time":0.3969404362},
{"learn":[5.227632786],"iteration":421,"passed_time":0.2890103612,"remaining_time":0.3958483147},
{"learn":[5.225567755],"iteration":422,"passed_time":0.28963992,"remaining_time":0.3950880233},
{"learn":[5.223802106],"iteration":423,"passed_time":0.2902874255,"remaining_time":0.3943527289},
{"learn":[5.222560162],"iteration":424,"passed_time":0.2908369325,"remaining_time":0.3934852616},
{"learn":[5.220563263],"iteration":425,"passed_time":0.2914602273,"remaining_time":0.39271871},
{"learn":[5.218915442],"iteration":426,"passed_time":0.2921572358,"remaining_time":0.3920517474},
{"learn":[5.216818077],"iteration":427,"passed_time":0.2929853555,"remaining_time":0.3915598676},
{"learn":[5.214791468],"iteration":428,"passed_time":0.2938364457,"remaining_time":0.3910969942},
{"learn":[5.212955206],"iteration":429,"passed_time":0.2945514625,"remaining_time":0.3904519387},
{"learn":[5.210892649],"iteration":430,"passed_time":0.2952511351,"remaining_time":0.3897863014},
{"learn":[5.210004949],"iteration":431,"passed_time":0.2956978422,"remaining_time":0.3887879037},
{"learn":[5.208114408],"iteration":432,"passed_time":0.296397612,"remaining_time":0.3881234319},
{"learn":[5.206280429],"iteration":433,"passed_time":0.297035096,"remaining_time":0.3873775676},
{"learn":[5.204676073],"iteration":434,"passed_time":0.2977351303,"remaining_time":0.3867134451},
{"learn":[5.202504746],"iteration":435,"passed_time":0.2983556883,"remaining_time":0.3859463491},
{"learn":[5.200715308],"iteration":436,"passed_time":0.2990398328,"remaining_time":0.3852618441},
{"learn":[5.197066569],"iteration":437,"passed_time":0.2997283473,"remaining_time":0.3845829479},
{"learn":[5.194195536],"iteration":438,"passed_time":0.300355774,"remaining_time":0.3838259435},
{"learn":[5.191664245],"iteration":439,"passed_time":0.3010076403,"remaining_time":0.3831006331},
{"learn":[5.18928454],"iteration":440,"passed_time":0.3016898573,"remaining_time":0.3824141275},
{"learn":[5.187677346],"iteration":441,"passed_time":0.3023476132,"remaining_time":0.3816967605},
{"learn":[5.18611894],"iteration":442,"passed_time":0.3030626304,"remaining_time":0.3810516594},
{"learn":[5.183733328],"iteration":443,"passed_time":0.3036778354,"remaining_time":0.3802812533},
{"learn":[5.182083659],"iteration":444,"passed_time":0.3043926236,"remaining_time":0.379635744},
{"learn":[5.179365231],"iteration":445,"passed_time":0.3051545976,"remaining_time":0.3790485361},
{"learn":[5.177023119],"iteration":446,"passed_time":0.3059471728,"remaining_time":0.3784984039},
{"learn":[5.175135606],"iteration":447,"passed_time":0.3066585244,"remaining_time":0.3778471104},
{"learn":[5.173900562],"iteration":448,"passed_time":0.3073054292,"remaining_time":0.3771164621},
{"learn":[5.172416095],"iteration":449,"passed_time":0.3079797239,"remaining_time":0.3764196625},
{"learn":[5.170983426],"iteration":450,"passed_time":0.3086760099,"remaining_time":0.3757497326},
{"learn":[5.169027439],"iteration":451,"passed_time":0.3093712881,"remaining_time":0.3750784643},
{"learn":[5.167345289],"iteration":452,"passed_time":0.3100360197,"remaining_time":0.3743702048},
{"learn":[5.164609666],"iteration":453,"passed_time":0.310776844,"remaining_time":0.3737536494},
{"learn":[5.162789683],"iteration":454,"passed_time":0.3114678775,"remaining_time":0.3730769082},
{"learn":[5.161272846],"iteration":455,"passed_time":0.3121726939,"remaining_time":0.3724165471},
{"learn":[5.160226612],"iteration":456,"passed_time":0.3128977949,"remaining_time":0.3717800933},
{"learn":[5.158800091],"iteration":457,"passed_time":0.3135977313,"remaining_time":0.3711134724},
{"learn":[5.157387131],"iteration":458,"passed_time":0.3143621015,"remaining_time":0.3705226512},
{"learn":[5.155805189],"iteration":459,"passed_time":0.3150515039,"remaining_time":0.3698430698},
{"learn":[5.154227742],"iteration":460,"passed_time":0.3157987075,"remaining_time":0.3692310267},
{"learn":[5.152545462],"iteration":461,"passed_time":0.3164103576,"remaining_time":0.3684605463},
{"learn":[5.150804038],"iteration":462,"passed_time":0.3170360623,"remaining_time":0.3677070528},
{"learn":[5.14886445],"iteration":463,"passed_time":0.3177135096,"remaining_time":0.3670138817},
{"learn":[5.14746514],"iteration":464,"passed_time":0.3184340558,"remaining_time":0.3663703653},
{"learn":[5.145692347],"iteration":465,"passed_time":0.3190436627,"remaining_time":0.3655993903},
{"learn":[5.144964968],"iteration":466,"passed_time":0.3195049514,"remaining_time":0.3646598267},
{"learn":[5.14366654],"iteration":467,"passed_time":0.3201720131,"remaining_time":0.36395622},
{"learn":[5.141808346],"iteration":468,"passed_time":0.3208379637,"remaining_time":0.3632515112},
{"learn":[5.13967506],"iteration":469,"passed_time":0.3214611283,"remaining_time":0.3624987191},
{"learn":[5.137787746],"iteration":470,"passed_time":0.3221251477,"remaining_time":0.3617923634},
{"learn":[5.136286016],"iteration":471,"passed_time":0.3227479543,"remaining_time":0.3610400845},
{"learn":[5.134700571],"iteration":472,"passed_time":0.3233321002,"remaining_time":0.3602452786},
{"learn":[5.133426045],"iteration":473,"passed_time":0.3239446506,"remaining_time":0.3594828823},
{"learn":[5.131459972],"iteration":474,"passed_time":0.3245847322,"remaining_time":0.3587515461},
{"learn":[5.129830954],"iteration":475,"passed_time":0.3251825113,"remaining_time":0.3579740251},
{"learn":[5.127264562],"iteration":476,"passed_time":0.3258196701,"remaining_time":0.3572404349},
{"learn":[5.125000568],"iteration":477,"passed_time":0.3264932331,"remaining_time":0.3565470035},
{"learn":[5.123504441],"iteration":478,"passed_time":0.3271449742,"remaining_time":0.3558299197},
{"learn":[5.121260712],"iteration":479,"passed_time":0.3277524982,"remaining_time":0.3550652064},
{"learn":[5.119555181],"iteration":480,"passed_time":0.3284289361,"remaining_time":0.3543755048},
{"learn":[5.118934014],"iteration":481,"passed_time":0.3288297561,"remaining_time":0.3533896549},
{"learn":[5.117427961],"iteration":482,"passed_time":0.32947808,"remaining_time":0.352671154},
{"learn":[5.1159761],"iteration":483,"passed_time":0.3301427067,"remaining_time":0.3519703236},
{"learn":[5.113904653],"iteration":484,"passed_time":0.3308010313,"remaining_time":0.3512629508},
{"learn":[5.11191646],"iteration":485,"passed_time":0.331606969,"remaining_time":0.3507118973},
{"learn":[5.10969012],"iteration":486,"passed_time":0.3323416843,"remaining_time":0.3500847722},
{"learn":[5.108061795],"iteration":487,"passed_time":0.3329802418,"remaining_time":0.3493563193},
{"learn":[5.106641113],"iteration":488,"passed_time":0.3336120931,"remaining_time":0.3486212261},
{"learn":[5.105193342],"iteration":489,"passed_time":0.3342530597,"remaining_time":0.3478960417},
{"learn":[5.104241691],"iteration":490,"passed_time":0.3349124007,"remaining_time":0.3471902484},
{"learn":[5.102884832],"iteration":491,"passed_time":0.3355402602,"remaining_time":0.3464521386},
{"learn":[5.10115623],"iteration":492,"passed_time":0.3361622748,"remaining_time":0.3457084652},
{"learn":[5.100323599],"iteration":493,"passed_time":0.336778204,"remaining_time":0.3449590511},
{"learn":[5.099553902],"iteration":494,"passed_time":0.3374544075,"remaining_time":0.3442716683},
{"learn":[5.098165573],"iteration":495,"passed_time":0.3381319685,"remaining_time":0.3435857099},
{"learn":[5.096032368],"iteration":496,"passed_time":0.3388549098,"remaining_time":0.3429457135},
{"learn":[5.094801517],"iteration":497,"passed_time":0.3395174655,"remaining_time":0.3422445134},
{"learn":[5.09397602],"iteration":498,"passed_time":0.3402273968,"remaining_time":0.3415910336},
{"learn":[5.09283838],"iteration":499,"passed_time":0.3409572188,"remaining_time":0.3409572188},
{"learn":[5.091830746],"iteration":500,"passed_time":0.3415671175,"remaining_time":0.3402035761},
{"learn":[5.090273051],"iteration":501,"passed_time":0.3422418904,"remaining_time":0.3395148634},
{"learn":[5.088733322],"iteration":502,"passed_time":0.3430331718,"remaining_time":0.3389413248},
{"learn":[5.087093288],"iteration":503,"passed_time":0.3436477873,"remaining_time":0.3381930605},
{"learn":[5.084832735],"iteration":504,"passed_time":0.3442757989,"remaining_time":0.3374584563},
{"learn":[5.083404947],"iteration":505,"passed_time":0.3450306173,"remaining_time":0.336848073},
{"learn":[5.08251745],"iteration":506,"passed_time":0.3457662817,"remaining_time":0.3362184948},
{"learn":[5.081328012],"iteration":507,"passed_time":0.3463907396,"remaining_time":0.3354807951},
{"learn":[5.079123028],"iteration":508,"passed_time":0.3470705956,"remaining_time":0.3347969792},
{"learn":[5.077149797],"iteration":509,"passed_time":0.3476798263,"remaining_time":0.3340453233},
{"learn":[5.07543215],"iteration":510,"passed_time":0.3483408022,"remaining_time":0.3333437422},
{"learn":[5.073794666],"iteration":511,"passed_time":0.3490884605,"remaining_time":0.3327249389},
{"learn":[5.072016419],"iteration":512,"passed_time":0.3498309617,"remaining_time":0.3321007375},
{"learn":[5.070987715],"iteration":513,"passed_time":0.3505096516,"remaining_time":0.3314157406},
{"learn":[5.069880608],"iteration":514,"passed_time":0.3512094685,"remaining_time":0.3307506645},
{"learn":[5.068075532],"iteration":515,"passed_time":0.3519611768,"remaining_time":0.3301341271},
{"learn":[5.066052054],"iteration":516,"passed_time":0.3526069594,"remaining_time":0.3294181071},
{"learn":[5.064588197],"iteration":517,"passed_time":0.353249655,"remaining_time":0.3286994859},
{"learn":[5.062981414],"iteration":518,"passed_time":0.3538871585,"remaining_time":0.3279763453},
{"learn":[5.061964173],"iteration":519,"passed_time":0.3545517694,"remaining_time":0.3272785564},
{"learn":[5.06086023],"iteration":520,"passed_time":0.3552615804,"remaining_time":0.3266224511},
{"learn":[5.059900302],"iteration":521,"passed_time":0.3559459002,"remaining_time":0.3259427975},
{"learn":[5.058479391],"iteration":522,"passed_time":0.3566225369,"remaining_time":0.3252561187},
{"learn":[5.056262825],"iteration":523,"passed_time":0.3572523495,"remaining_time":0.3245269434},
{"learn":[5.056020073],"iteration":524,"passed_time":0.3576005117,"remaining_time":0.3235433201},
{"learn":[5.055259164],"iteration":525,"passed_time":0.3582723427,"remaining_time":0.3228537841},
{"learn":[5.053337859],"iteration":526,"passed_time":0.3589028208,"remaining_time":0.3221271997},
{"learn":[5.051935305],"iteration":527,"passed_time":0.359495898,"remaining_time":0.3213675452},
{"learn":[5.050391217],"iteration":528,"passed_time":0.3601457113,"remaining_time":0.3206590359},
{"learn":[5.049467802],"iteration":529,"passed_time":0.360781973,"remaining_time":0.3199387308},
{"learn":[5.047782094],"iteration":530,"passed_time":0.3615196789,"remaining_time":0.3193083416},
{"learn":[5.045645064],"iteration":531,"passed_time":0.3622311677,"remaining_time":0.3186544859},
{"learn":[5.045349109],"iteration":532,"passed_time":0.3626206056,"remaining_time":0.3177182417},
{"learn":[5.044466417],"iteration":533,"passed_time":0.3633384022,"remaining_time":0.3170705907},
{"learn":[5.043318328],"iteration":534,"passed_time":0.3640159677,"remaining_time":0.3163877103},
{"learn":[5.041910158],"iteration":535,"passed_time":0.3648080055,"remaining_time":0.3158039451},
{"learn":[5.040582262],"iteration":536,"passed_time":0.365543235,"remaining_time":0.3151704242},
{"learn":[5.039275272],"iteration":537,"passed_time":0.3664056173,"remaining_time":0.314645716},
{"learn":[5.037667306],"iteration":538,"passed_time":0.3672791793,"remaining_time":0.3141293166},
{"learn":[5.035237894],"iteration":539,"passed_time":0.3680298335,"remaining_time":0.3135068952},
{"learn":[5.034307838],"iteration":540,"passed_time":0.3687548854,"remaining_time":0.312862278},
{"learn":[5.032985676],"iteration":541,"passed_time":0.3694390758,"remaining_time":0.3121828352},
{"learn":[5.031796366],"iteration":542,"passed_time":0.3701183216,"remaining_time":0.3114992136},
{"learn":[5.031119994],"iteration":543,"passed_time":0.3708606153,"remaining_time":0.310868457},
{"learn":[5.03004769],"iteration":544,"passed_time":0.371598749,"remaining_time":0.310233818},
{"learn":[5.0285172],"iteration":545,"passed_time":0.3722976078,"remaining_time":0.3095661427},
{"learn":[5.02667778],"iteration":546,"passed_time":0.3730061576,"remaining_time":0.3089063792},
{"learn":[5.025493912],"iteration":547,"passed_time":0.3736805357,"remaining_time":0.3082182521},
{"learn":[5.024276785],"iteration":548,"passed_time":0.3743693173,"remaining_time":0.3075420074},
{"learn":[5.023310875],"iteration":549,"passed_time":0.3750984192,"remaining_time":0.3068987066},
{"learn":[5.02213108],"iteration":550,"passed_time":0.3757752952,"remaining_time":0.3062125364},
{"learn":[5.020839738],"iteration":551,"passed_time":0.3764678478,"remaining_time":0.3055391228},
{"learn":[5.019677022],"iteration":552,"passed_time":0.3771999101,"remaining_time":0.3048975765},
{"learn":[5.018260216],"iteration":553,"passed_time":0.3779546161,"remaining_time":0.3042739328},
{"learn":[5.016416415],"iteration":554,"passed_time":0.3786760408,"remaining_time":0.3036231318},
{"learn":[5.01519109],"iteration":555,"passed_time":0.3793000043,"remaining_time":0.3028942481},
{"learn":[5.014148616],"iteration":556,"passed_time":0.3799746966,"remaining_time":0.3022060873},
{"learn":[5.012300991],"iteration":557,"passed_time":0.3807006566,"remaining_time":0.3015585846},
{"learn":[5.010799757],"iteration":558,"passed_time":0.3813871056,"remaining_time":0.3008796307},
{"learn":[5.00897997],"iteration":559,"passed_time":0.3820489813,"remaining_time":0.3001813425},
{"learn":[5.007536435],"iteration":560,"passed_time":0.3827583662,"remaining_time":0.2995203614},
{"learn":[5.006502343],"iteration":561,"passed_time":0.3834349921,"remaining_time":0.2988336771},
{"learn":[5.005355112],"iteration":562,"passed_time":0.3841336768,"remaining_time":0.2981641506},
{"learn":[5.003683668],"iteration":563,"passed_time":0.384864237,"remaining_time":0.297519162},
{"learn":[5.002212512],"iteration":564,"passed_time":0.385583172,"remaining_time":0.2968649201},
{"learn":[5.000479759],"iteration":565,"passed_time":0.386323988,"remaining_time":0.2962272276},
{"learn":[4.998958408],"iteration":566,"passed_time":0.3872760384,"remaining_time":0.2957504843},
{"learn":[4.998055938],"iteration":567,"passed_time":0.3879685856,"remaining_time":0.2950746989},
{"learn":[4.996235269],"iteration":568,"passed_time":0.3886622257,"remaining_time":0.2943996824},
{"learn":[4.995373817],"iteration":569,"passed_time":0.3894744204,"remaining_time":0.2938140364},
{"learn":[4.994417882],"iteration":570,"passed_time":0.3903410028,"remaining_time":0.2932684592},
{"learn":[4.99348533],"iteration":571,"passed_time":0.3911471509,"remaining_time":0.2926765395},
{"learn":[4.992670264],"iteration":572,"passed_time":0.391883587,"remaining_time":0.2920319226},
{"learn":[4.992152306],"iteration":573,"passed_time":0.3923368793,"remaining_time":0.2911768477},
{"learn":[4.991103853],"iteration":574,"passed_time":0.3929993908,"remaining_time":0.2904778106},
{"learn":[4.990200566],"iteration":575,"passed_time":0.393808892,"remaining_time":0.2898871011},
{"learn":[4.988582926],"iteration":576,"passed_time":0.3946611384,"remaining_time":0.2893269698},
{"learn":[4.986954585],"iteration":577,"passed_time":0.3954037612,"remaining_time":0.2886857911},
{"learn":[4.985682921],"iteration":578,"passed_time":0.3961846504,"remaining_time":0.2880720861},
{"learn":[4.983656516],"iteration":579,"passed_time":0.3970659442,"remaining_time":0.2875305113},
{"learn":[4.982697884],"iteration":580,"passed_time":0.3978178373,"remaining_time":0.2868944472},
{"learn":[4.981509667],"iteration":581,"passed_time":0.3985864353,"remaining_time":0.2862699828},
{"learn":[4.980571857],"iteration":582,"passed_time":0.3992572979,"remaining_time":0.285575117},
{"learn":[4.979586021],"iteration":583,"passed_time":0.400041651,"remaining_time":0.284961176},
{"learn":[4.978826449],"iteration":584,"passed_time":0.400805078,"remaining_time":0.2843318074},
{"learn":[4.977594762],"iteration":585,"passed_time":0.4015301517,"remaining_time":0.2836748853},
{"learn":[4.976299069],"iteration":586,"passed_time":0.4023232022,"remaining_time":0.283065558},
{"learn":[4.975687717],"iteration":587,"passed_time":0.4030650595,"remaining_time":0.2824197356},
{"learn":[4.975099395],"iteration":588,"passed_time":0.4037293054,"remaining_time":0.2817194304},
{"learn":[4.973395154],"iteration":589,"passed_time":0.4044743129,"remaining_time":0.2810753699},
{"learn":[4.971336448],"iteration":590,"passed_time":0.4052459015,"remaining_time":0.2804493633},
{"learn":[4.970086483],"iteration":591,"passed_time":0.4059964173,"remaining_time":0.2798083417},
{"learn":[4.968842926],"iteration":592,"passed_time":0.406756139,"remaining_time":0.2791732691},
{"learn":[4.967145998],"iteration":593,"passed_time":0.4076422897,"remaining_time":0.2786241913},
{"learn":[4.966394084],"iteration":594,"passed_time":0.4084342138,"remaining_time":0.278009843},
{"learn":[4.965489491],"iteration":595,"passed_time":0.4092470385,"remaining_time":0.2774090663},
{"learn":[4.964535983],"iteration":596,"passed_time":0.4098961883,"remaining_time":0.2766970919},
{"learn":[4.963901632],"iteration":597,"passed_time":0.4106569867,"remaining_time":0.2760603824},
{"learn":[4.962606325],"iteration":598,"passed_time":0.4114341408,"remaining_time":0.2754342078},
{"learn":[4.961288394],"iteration":599,"passed_time":0.412250443,"remaining_time":0.2748336287},
{"learn":[4.959987331],"iteration":600,"passed_time":0.4129692276,"remaining_time":0.2741675903},
{"learn":[4.958499739],"iteration":601,"passed_time":0.4136444175,"remaining_time":0.2734725551},
{"learn":[4.956953907],"iteration":602,"passed_time":0.4144198955,"remaining_time":0.2728436128},
{"learn":[4.955635205],"iteration":603,"passed_time":0.4152377193,"remaining_time":0.2722419484},
{"learn":[4.95375998],"iteration":604,"passed_time":0.4160009474,"remaining_time":0.2716039243},
{"learn":[4.952364937],"iteration":605,"passed_time":0.4168610067,"remaining_time":0.2710284433},
{"learn":[4.950625725],"iteration":606,"passed_time":0.4177289494,"remaining_time":0.2704571287},
{"learn":[4.9500437],"iteration":607,"passed_time":0.4185352348,"remaining_time":0.2698450856},
{"learn":[4.949493617],"iteration":608,"passed_time":0.4193096182,"remaining_time":0.2692119223},
{"learn":[4.948778583],"iteration":609,"passed_time":0.4201092084,"remaining_time":0.2685944119},
{"learn":[4.947083724],"iteration":610,"passed_time":0.421099111,"remaining_time":0.26809747},
{"learn":[4.946460045],"iteration":611,"passed_time":0.4218634403,"remaining_time":0.2674559066},
{"learn":[4.945468049],"iteration":612,"passed_time":0.4225896682,"remaining_time":0.2667898884},
{"learn":[4.94462259],"iteration":613,"passed_time":0.4233663196,"remaining_time":0.2661553736},
{"learn":[4.943499463],"iteration":614,"passed_time":0.424139921,"remaining_time":0.2655184871},
{"learn":[4.941619332],"iteration":615,"passed_time":0.4248835684,"remaining_time":0.2648624842},
{"learn":[4.940647371],"iteration":616,"passed_time":0.4256053754,"remaining_time":0.2641926399},
{"learn":[4.939847945],"iteration":617,"passed_time":0.4264094167,"remaining_time":0.2635734582},
{"learn":[4.938775942],"iteration":618,"passed_time":0.4271364721,"remaining_time":0.2629062938},
{"learn":[4.937313026],"iteration":619,"passed_time":0.4278374298,"remaining_time":0.2622229409},
{"learn":[4.936353082],"iteration":620,"passed_time":0.4285300299,"remaining_time":0.2615344305},
{"learn":[4.934987975],"iteration":621,"passed_time":0.4291903924,"remaining_time":0.2608263156},
{"learn":[4.933272778],"iteration":622,"passed_time":0.4298827552,"remaining_time":0.2601377186},
{"learn":[4.932230126],"iteration":623,"passed_time":0.4305643543,"remaining_time":0.2594426237},
{"learn":[4.931104328],"iteration":624,"passed_time":0.4312714384,"remaining_time":0.258762863},
{"learn":[4.930617792],"iteration":625,"passed_time":0.4319443201,"remaining_time":0.258062581},
{"learn":[4.929134968],"iteration":626,"passed_time":0.4326614335,"remaining_time":0.2573886997},
{"learn":[4.928032687],"iteration":627,"passed_time":0.4334155302,"remaining_time":0.2567365879},
{"learn":[4.927226639],"iteration":628,"passed_time":0.4341575829,"remaining_time":0.2560770481},
{"learn":[4.925973679],"iteration":629,"passed_time":0.4348465306,"remaining_time":0.2553860577},
{"learn":[4.924021974],"iteration":630,"passed_time":0.4355765498,"remaining_time":0.2547190917},
{"learn":[4.923148186],"iteration":631,"passed_time":0.4363638894,"remaining_time":0.2540853027},
{"learn":[4.921877493],"iteration":632,"passed_time":0.437090543,"remaining_time":0.253415844},
{"learn":[4.920658284],"iteration":633,"passed_time":0.4379877956,"remaining_time":0.2528446896},
{"learn":[4.919468646],"iteration":634,"passed_time":0.4389227813,"remaining_time":0.2522941972},
{"learn":[4.918262759],"iteration":635,"passed_time":0.4397073883,"remaining_time":0.2516564298},
{"learn":[4.917233642],"iteration":636,"passed_time":0.4404987275,"remaining_time":0.2510220378},
{"learn":[4.916315385],"iteration":637,"passed_time":0.4411519439,"remaining_time":0.2503087832},
{"learn":[4.915161715],"iteration":638,"passed_time":0.4418932332,"remaining_time":0.2496454729},
{"learn":[4.913760533],"iteration":639,"passed_time":0.4426899808,"remaining_time":0.2490131142},
{"learn":[4.912868894],"iteration":640,"passed_time":0.4433788536,"remaining_time":0.248319826},
{"learn":[4.911488132],"iteration":641,"passed_time":0.4440116341,"remaining_time":0.2475952726},
{"learn":[4.911161533],"iteration":642,"passed_time":0.4447070401,"remaining_time":0.246905775},
{"learn":[4.910412917],"iteration":643,"passed_time":0.4457040586,"remaining_time":0.2463829889},
{"learn":[4.909619933],"iteration":644,"passed_time":0.4464173335,"remaining_time":0.2457025634},
{"learn":[4.908546042],"iteration":645,"passed_time":0.4472179699,"remaining_time":0.2450699092},
{"learn":[4.906984654],"iteration":646,"passed_time":0.4479676843,"remaining_time":0.2444089529},
{"learn":[4.905261588],"iteration":647,"passed_time":0.4486723659,"remaining_time":0.2437232605},
{"learn":[4.903982378],"iteration":648,"passed_time":0.4493731509,"remaining_time":0.2430354021},
{"learn":[4.902691843],"iteration":649,"passed_time":0.4501572254,"remaining_time":0.2423923521},
{"learn":[4.902120511],"iteration":650,"passed_time":0.4510673949,"remaining_time":0.2418164683},
{"learn":[4.901626464],"iteration":651,"passed_time":0.4518727164,"remaining_time":0.2411835971},
{"learn":[4.900998913],"iteration":652,"passed_time":0.4526608285,"remaining_time":0.2405410528},
{"learn":[4.900252359],"iteration":653,"passed_time":0.4535512368,"remaining_time":0.2399521834},
{"learn":[4.899233441],"iteration":654,"passed_time":0.4543269189,"remaining_time":0.2393019649},
{"learn":[4.897774626],"iteration":655,"passed_time":0.4551461709,"remaining_time":0.2386742115},
{"learn":[4.897135563],"iteration":656,"passed_time":0.4559761084,"remaining_time":0.2380514539},
{"learn":[4.896045184],"iteration":657,"passed_time":0.4568514234,"remaining_time":0.2374516517},
{"learn":[4.89419148],"iteration":658,"passed_time":0.4576832996,"remaining_time":0.2368285359},
{"learn":[4.892721728],"iteration":659,"passed_time":0.4583950022,"remaining_time":0.2361428799},
{"learn":[4.89123157],"iteration":660,"passed_time":0.4591084131,"remaining_time":0.2354580212},
{"learn":[4.891068007],"iteration":661,"passed_time":0.4594664491,"remaining_time":0.2345916311},
{"learn":[4.890179923],"iteration":662,"passed_time":0.4602369193,"remaining_time":0.233936413},
{"learn":[4.889240981],"iteration":663,"passed_time":0.4609862905,"remaining_time":0.2332701711},
{"learn":[4.887812947],"iteration":664,"passed_time":0.4617963151,"remaining_time":0.2326342339},
{"learn":[4.887075718],"iteration":665,"passed_time":0.4625304099,"remaining_time":0.2319596951},
{"learn":[4.885890674],"iteration":666,"passed_time":0.4632741467,"remaining_time":0.2312897914},
{"learn":[4.884441029],"iteration":667,"passed_time":0.4641527292,"remaining_time":0.2306866858},
{"learn":[4.883812468],"iteration":668,"passed_time":0.4648716229,"remaining_time":0.2300037476},
{"learn":[4.883117154],"iteration":669,"passed_time":0.4656287073,"remaining_time":0.2293395126},
{"learn":[4.88191305],"iteration":670,"passed_time":0.4663927609,"remaining_time":0.2286784178},
{"learn":[4.88042259],"iteration":671,"passed_time":0.4670509707,"remaining_time":0.2279653547},
{"learn":[4.879168451],"iteration":672,"passed_time":0.467702811,"remaining_time":0.2272493599},
{"learn":[4.878123701],"iteration":673,"passed_time":0.4685050351,"remaining_time":0.2266062929},
{"learn":[4.877471188],"iteration":674,"passed_time":0.4693658996,"remaining_time":0.2259909887},
{"learn":[4.875907516],"iteration":675,"passed_time":0.4701478842,"remaining_time":0.2253371516},
{"learn":[4.875356512],"iteration":676,"passed_time":0.4709412786,"remaining_time":0.2246883796},
{"learn":[4.874729961],"iteration":677,"passed_time":0.4716804127,"remaining_time":0.2240134113},
{"learn":[4.873761351],"iteration":678,"passed_time":0.4724467459,"remaining_time":0.2233511126},
{"learn":[4.87269833],"iteration":679,"passed_time":0.4731345416,"remaining_time":0.222651549},
{"learn":[4.871311487],"iteration":680,"passed_time":0.4741717949,"remaining_time":0.222115716},
{"learn":[4.870340567],"iteration":681,"passed_time":0.4749015479,"remaining_time":0.2214350326},
{"learn":[4.869039951],"iteration":682,"passed_time":0.4757378826,"remaining_time":0.2208036732},
{"learn":[4.868415211],"iteration":683,"passed_time":0.4767239777,"remaining_time":0.220240902},
{"learn":[4.867932631],"iteration":684,"passed_time":0.4774785845,"remaining_time":0.219570444},
{"learn":[4.866905276],"iteration":685,"passed_time":0.4781380678,"remaining_time":0.2188562001},
{"learn":[4.866294876],"iteration":686,"passed_time":0.4787869352,"remaining_time":0.2181372791},
{"learn":[4.865351904],"iteration":687,"passed_time":0.4794735471,"remaining_time":0.2174356783},
{"learn":[4.863908093],"iteration":688,"passed_time":0.4801355683,"remaining_time":0.2167230214},
{"learn":[4.862541858],"iteration":689,"passed_time":0.480794549,"remaining_time":0.2160091452},
{"learn":[4.861374837],"iteration":690,"passed_time":0.481408389,"remaining_time":0.215275242},
{"learn":[4.860446086],"iteration":691,"passed_time":0.4820803416,"remaining_time":0.2145675509},
{"learn":[4.859402003],"iteration":692,"passed_time":0.4828606037,"remaining_time":0.2139079442},
{"learn":[4.858418355],"iteration":693,"passed_time":0.4836682085,"remaining_time":0.2132600458},
{"learn":[4.857374343],"iteration":694,"passed_time":0.4845547912,"remaining_time":0.2126463472},
{"learn":[4.855547373],"iteration":695,"passed_time":0.4852631943,"remaining_time":0.2119540389},
{"learn":[4.854075902],"iteration":696,"passed_time":0.4861129101,"remaining_time":0.2113231159},
{"learn":[4.852812499],"iteration":697,"passed_time":0.4868504048,"remaining_time":0.2106430118},
{"learn":[4.851479262],"iteration":698,"passed_time":0.4876762998,"remaining_time":0.2100008101},
{"learn":[4.850667763],"iteration":699,"passed_time":0.4884997179,"remaining_time":0.209357022},
{"learn":[4.849501355],"iteration":700,"passed_time":0.4892675492,"remaining_time":0.2086890117},
{"learn":[4.848448585],"iteration":701,"passed_time":0.4899989188,"remaining_time":0.208005239},
{"learn":[4.848101422],"iteration":702,"passed_time":0.490659225,"remaining_time":0.2072913084},
{"learn":[4.84642222],"iteration":703,"passed_time":0.4912737009,"remaining_time":0.2065582606},
{"learn":[4.844956555],"iteration":704,"passed_time":0.4919063276,"remaining_time":0.2058331442},
{"learn":[4.844107274],"iteration":705,"passed_time":0.4926475821,"remaining_time":0.2051535257},
{"learn":[4.84324001],"iteration":706,"passed_time":0.4933010713,"remaining_time":0.2044373605},
{"learn":[4.842099304],"iteration":707,"passed_time":0.493999377,"remaining_time":0.203739856},
{"learn":[4.840577591],"iteration":708,"passed_time":0.4946877493,"remaining_time":0.2030382723},
{"learn":[4.838751083],"iteration":709,"passed_time":0.4953628739,"remaining_time":0.2023313147},
{"learn":[4.83759516],"iteration":710,"passed_time":0.4960628396,"remaining_time":0.2016345438},
{"learn":[4.836986496],"iteration":711,"passed_time":0.496774371,"remaining_time":0.2009424422},
{"learn":[4.835200003],"iteration":712,"passed_time":0.4975667465,"remaining_time":0.2002828278},
{"learn":[4.834518948],"iteration":713,"passed_time":0.4984145345,"remaining_time":0.1996450376},
{"learn":[4.833569896],"iteration":714,"passed_time":0.4991777266,"remaining_time":0.19897294},
{"learn":[4.83258966],"iteration":715,"passed_time":0.499915497,"remaining_time":0.1982905044},
{"learn":[4.831511256],"iteration":716,"passed_time":0.5006837859,"remaining_time":0.1976199601},
{"learn":[4.830501884],"iteration":717,"passed_time":0.5015093126,"remaining_time":0.1969716242},
{"learn":[4.829652914],"iteration":718,"passed_time":0.5022359228,"remaining_time":0.1962841367},
{"learn":[4.828311735],"iteration":719,"passed_time":0.5029424381,"remaining_time":0.1955887259},
{"learn":[4.827288726],"iteration":720,"passed_time":0.503725299,"remaining_time":0.1949228272},
{"learn":[4.826141909],"iteration":721,"passed_time":0.5045824792,"remaining_time":0.1942852205},
{"learn":[4.82503713],"iteration":722,"passed_time":0.505569206,"remaining_time":0.1936966391},
{"learn":[4.823521065],"iteration":723,"passed_time":0.5063705038,"remaining_time":0.1930362694},
{"learn":[4.82152105],"iteration":724,"passed_time":0.5071169431,"remaining_time":0.1923547025},
{"learn":[4.82063078],"iteration":725,"passed_time":0.5079132662,"remaining_time":0.1916917836},
{"learn":[4.819886644],"iteration":726,"passed_time":0.5087499208,"remaining_time":0.1910436429},
{"learn":[4.818345569],"iteration":727,"passed_time":0.5095116807,"remaining_time":0.1903670016},
{"learn":[4.816970512],"iteration":728,"passed_time":0.5102875402,"remaining_time":0.1896953682},
{"learn":[4.815859459],"iteration":729,"passed_time":0.5110674191,"remaining_time":0.1890249358},
{"learn":[4.814550719],"iteration":730,"passed_time":0.5117907241,"remaining_time":0.1883333855},
{"learn":[4.813280125],"iteration":731,"passed_time":0.5125649252,"remaining_time":0.1876603825},
{"learn":[4.812155824],"iteration":732,"passed_time":0.5133040915,"remaining_time":0.1869743417},
{"learn":[4.811570998],"iteration":733,"passed_time":0.5139657796,"remaining_time":0.1862600782},
{"learn":[4.81055688],"iteration":734,"passed_time":0.5146310292,"remaining_time":0.1855472418},
{"learn":[4.809202216],"iteration":735,"passed_time":0.5154180956,"remaining_time":0.1848782299},
{"learn":[4.808193038],"iteration":736,"passed_time":0.5162056923,"remaining_time":0.1842090869},
{"learn":[4.807568969],"iteration":737,"passed_time":0.5168874567,"remaining_time":0.183502051},
{"learn":[4.8071664],"iteration":738,"passed_time":0.5176162143,"remaining_time":0.1828116805},
{"learn":[4.806583063],"iteration":739,"passed_time":0.5187245908,"remaining_time":0.182254586},
{"learn":[4.8058723],"iteration":740,"passed_time":0.5194913714,"remaining_time":0.1815766062},
{"learn":[4.804987119],"iteration":741,"passed_time":0.5202993358,"remaining_time":0.1809127071},
{"learn":[4.804485652],"iteration":742,"passed_time":0.5210486401,"remaining_time":0.1802281299},
{"learn":[4.803253472],"iteration":743,"passed_time":0.5217981171,"remaining_time":0.1795434381},
{"learn":[4.802445549],"iteration":744,"passed_time":0.5225357461,"remaining_time":0.1788545171},
{"learn":[4.801981126],"iteration":745,"passed_time":0.5232200675,"remaining_time":0.1781473152},
{"learn":[4.800950064],"iteration":746,"passed_time":0.5240281448,"remaining_time":0.1774820892},
{"learn":[4.799975505],"iteration":747,"passed_time":0.5248944019,"remaining_time":0.1768360819},
{"learn":[4.799363103],"iteration":748,"passed_time":0.5257152961,"remaining_time":0.1761742848},
{"learn":[4.798216843],"iteration":749,"passed_time":0.5265203728,"remaining_time":0.1755067909},
{"learn":[4.797248009],"iteration":750,"passed_time":0.5272775304,"remaining_time":0.1748230427},
{"learn":[4.796212995],"iteration":751,"passed_time":0.528001858,"remaining_time":0.1741282723},
{"learn":[4.794794436],"iteration":752,"passed_time":0.5288084191,"remaining_time":0.1734603978},
{"learn":[4.79296241],"iteration":753,"passed_time":0.5295582037,"remaining_time":0.1727736314},
{"learn":[4.792538113],"iteration":754,"passed_time":0.5303978217,"remaining_time":0.1721158494},
{"learn":[4.791310478],"iteration":755,"passed_time":0.5312245433,"remaining_time":0.171453424},
{"learn":[4.789394289],"iteration":756,"passed_time":0.5319980599,"remaining_time":0.1707734855},
{"learn":[4.787989827],"iteration":757,"passed_time":0.5327886692,"remaining_time":0.1700987572},
{"learn":[4.78752571],"iteration":758,"passed_time":0.5335104092,"remaining_time":0.1694018559},
{"learn":[4.786206978],"iteration":759,"passed_time":0.5341958186,"remaining_time":0.1686934164},
{"learn":[4.785690652],"iteration":760,"passed_time":0.535043478,"remaining_time":0.1680359937},
{"learn":[4.784979413],"iteration":761,"passed_time":0.5357621356,"remaining_time":0.1673377799},
{"learn":[4.78417189],"iteration":762,"passed_time":0.536596723,"remaining_time":0.1666755221},
{"learn":[4.783818392],"iteration":763,"passed_time":0.5373728743,"remaining_time":0.1659947622},
{"learn":[4.783122099],"iteration":764,"passed_time":0.5380715198,"remaining_time":0.165289944},
{"learn":[4.782246182],"iteration":765,"passed_time":0.5388560506,"remaining_time":0.1646113784},
{"learn":[4.780871003],"iteration":766,"passed_time":0.5396427268,"remaining_time":0.1639331882},
{"learn":[4.779877073],"iteration":767,"passed_time":0.5403934923,"remaining_time":0.1632438675},
{"learn":[4.778875031],"iteration":768,"passed_time":0.5411023571,"remaining_time":0.1625418004},
{"learn":[4.777736351],"iteration":769,"passed_time":0.5418235052,"remaining_time":0.1618433847},
{"learn":[4.777177987],"iteration":770,"passed_time":0.5425916577,"remaining_time":0.1611588711},
{"learn":[4.776650654],"iteration":771,"passed_time":0.5434567929,"remaining_time":0.1605027834},
{"learn":[4.775968014],"iteration":772,"passed_time":0.544246678,"remaining_time":0.1598240568},
{"learn":[4.775326518],"iteration":773,"passed_time":0.5449621751,"remaining_time":0.1591233224},
{"learn":[4.774037179],"iteration":774,"passed_time":0.5458140995,"remaining_time":0.1584621579},
{"learn":[4.772011252],"iteration":775,"passed_time":0.5467216604,"remaining_time":0.1578165618},
{"learn":[4.770658507],"iteration":776,"passed_time":0.5474850208,"remaining_time":0.1571289056},
{"learn":[4.769791797],"iteration":777,"passed_time":0.5482474483,"remaining_time":0.1564407886},
{"learn":[4.768841914],"iteration":778,"passed_time":0.5490216833,"remaining_time":0.1557558306},
{"learn":[4.767937787],"iteration":779,"passed_time":0.5498295538,"remaining_time":0.1550801306},
{"learn":[4.767047955],"iteration":780,"passed_time":0.5506222944,"remaining_time":0.1543998495},
{"learn":[4.766337199],"iteration":781,"passed_time":0.5513413935,"remaining_time":0.1536987516},
{"learn":[4.765329094],"iteration":782,"passed_time":0.5520155773,"remaining_time":0.15298516},
{"learn":[4.764222232],"iteration":783,"passed_time":0.5527869635,"remaining_time":0.1522984491},
{"learn":[4.762993541],"iteration":784,"passed_time":0.5536312085,"remaining_time":0.1516314775},
{"learn":[4.761973223],"iteration":785,"passed_time":0.5543248052,"remaining_time":0.1509230386},
{"learn":[4.761000381],"iteration":786,"passed_time":0.5550337482,"remaining_time":0.1502187908},
{"learn":[4.759956782],"iteration":787,"passed_time":0.5558878299,"remaining_time":0.1495535786},
{"learn":[4.759422123],"iteration":788,"passed_time":0.5566967797,"remaining_time":0.1488758182},
{"learn":[4.758519158],"iteration":789,"passed_time":0.5574319423,"remaining_time":0.1481781112},
{"learn":[4.75734286],"iteration":790,"passed_time":0.5581837792,"remaining_time":0.1474847154},
{"learn":[4.756338343],"iteration":791,"passed_time":0.5589581894,"remaining_time":0.1467971003},
{"learn":[4.755327755],"iteration":792,"passed_time":0.5597534299,"remaining_time":0.1461147036},
{"learn":[4.754869069],"iteration":793,"passed_time":0.5605782096,"remaining_time":0.1454396866},
{"learn":[4.754123222],"iteration":794,"passed_time":0.5613318112,"remaining_time":0.1447459387},
{"learn":[4.752198349],"iteration":795,"passed_time":0.5620807698,"remaining_time":0.1440508506},
{"learn":[4.751009538],"iteration":796,"passed_time":0.5628679177,"remaining_time":0.1433653542},
{"learn":[4.750499638],"iteration":797,"passed_time":0.563580957,"remaining_time":0.1426608437},
{"learn":[4.748763714],"iteration":798,"passed_time":0.564304877,"remaining_time":0.1419590492},
{"learn":[4.747965278],"iteration":799,"passed_time":0.5649792667,"remaining_time":0.1412448167},
{"learn":[4.747028519],"iteration":800,"passed_time":0.5657523336,"remaining_time":0.140555199},
{"learn":[4.745969025],"iteration":801,"passed_time":0.5665393016,"remaining_time":0.1398688051},
{"learn":[4.744938989],"iteration":802,"passed_time":0.5672550166,"remaining_time":0.1391646803},
{"learn":[4.744040695],"iteration":803,"passed_time":0.5680317371,"remaining_time":0.1384753986},
{"learn":[4.743606735],"iteration":804,"passed_time":0.5688003888,"remaining_time":0.1377839451},
{"learn":[4.741801626],"iteration":805,"passed_time":0.5695312545,"remaining_time":0.1370832052},
{"learn":[4.740897949],"iteration":806,"passed_time":0.5702111216,"remaining_time":0.1363701939},
{"learn":[4.739767243],"iteration":807,"passed_time":0.5709454107,"remaining_time":0.1356701966},
{"learn":[4.738792175],"iteration":808,"passed_time":0.5717633254,"remaining_time":0.134989858},
{"learn":[4.73779447],"iteration":809,"passed_time":0.5726050887,"remaining_time":0.1343147739},
{"learn":[4.736993967],"iteration":810,"passed_time":0.57359001,"remaining_time":0.133672641},
{"learn":[4.73578358],"iteration":811,"passed_time":0.5744094111,"remaining_time":0.1329913415},
{"learn":[4.73514337],"iteration":812,"passed_time":0.5754474899,"remaining_time":0.1323600008},
{"learn":[4.734382412],"iteration":813,"passed_time":0.5761327311,"remaining_time":0.1316470368},
{"learn":[4.733844381],"iteration":814,"passed_time":0.5769023356,"remaining_time":0.1309532909},
{"learn":[4.732733005],"iteration":815,"passed_time":0.5776562372,"remaining_time":0.1302558182},
{"learn":[4.731828857],"iteration":816,"passed_time":0.5783473757,"remaining_time":0.129544149},
{"learn":[4.731611224],"iteration":817,"passed_time":0.5791317239,"remaining_time":0.1288532686},
{"learn":[4.731268767],"iteration":818,"passed_time":0.5798209708,"remaining_time":0.1281411425},
{"learn":[4.730839983],"iteration":819,"passed_time":0.5806165713,"remaining_time":0.1274524181},
{"learn":[4.72965704],"iteration":820,"passed_time":0.581444405,"remaining_time":0.126770461},
{"learn":[4.728471572],"iteration":821,"passed_time":0.58224605,"remaining_time":0.126082478},
{"learn":[4.727101182],"iteration":822,"passed_time":0.5829784674,"remaining_time":0.1253793302},
{"learn":[4.725727071],"iteration":823,"passed_time":0.5837389972,"remaining_time":0.1246821159},
{"learn":[4.725016004],"iteration":824,"passed_time":0.5843955225,"remaining_time":0.1239626866},
{"learn":[4.724072281],"iteration":825,"passed_time":0.585116795,"remaining_time":0.1232570488},
{"learn":[4.723422916],"iteration":826,"passed_time":0.5858266994,"remaining_time":0.1225489952},
{"learn":[4.722070043],"iteration":827,"passed_time":0.5867329388,"remaining_time":0.1218817216},
{"learn":[4.721334757],"iteration":828,"passed_time":0.5874853043,"remaining_time":0.1211821315},
{"learn":[4.719899937],"iteration":829,"passed_time":0.5883693758,"remaining_time":0.1205093902},
{"learn":[4.719277061],"iteration":830,"passed_time":0.5891106089,"remaining_time":0.1198070913},
{"learn":[4.718667224],"iteration":831,"passed_time":0.5898358063,"remaining_time":0.1191014609},
{"learn":[4.717915724],"iteration":832,"passed_time":0.5904843377,"remaining_time":0.1183804134},
{"learn":[4.717367238],"iteration":833,"passed_time":0.5911716919,"remaining_time":0.1176672672},
{"learn":[4.716253233],"iteration":834,"passed_time":0.5918469509,"remaining_time":0.1169517927},
{"learn":[4.715789535],"iteration":835,"passed_time":0.5925414268,"remaining_time":0.1162401842},
{"learn":[4.714992682],"iteration":836,"passed_time":0.5934037776,"remaining_time":0.1155613091},
{"learn":[4.714469847],"iteration":837,"passed_time":0.5941687927,"remaining_time":0.1148631795},
{"learn":[4.712994482],"iteration":838,"passed_time":0.5948987619,"remaining_time":0.1141581653},
{"learn":[4.712173864],"iteration":839,"passed_time":0.595567608,"remaining_time":0.1134414492},
{"learn":[4.711669323],"iteration":840,"passed_time":0.5963070447,"remaining_time":0.1127381928},
{"learn":[4.711544569],"iteration":841,"passed_time":0.5969954145,"remaining_time":0.1120252678},
{"learn":[4.711017443],"iteration":842,"passed_time":0.597622496,"remaining_time":0.1113009868},
{"learn":[4.710392833],"iteration":843,"passed_time":0.5982902576,"remaining_time":0.1105844552},
{"learn":[4.709956038],"iteration":844,"passed_time":0.5989956824,"remaining_time":0.1098749477},
{"learn":[4.708879303],"iteration":845,"passed_time":0.5998330352,"remaining_time":0.109189465},
{"learn":[4.708104962],"iteration":846,"passed_time":0.6005314149,"remaining_time":0.10847852},
{"learn":[4.707648031],"iteration":847,"passed_time":0.6012887312,"remaining_time":0.1077781688},
{"learn":[4.7070034],"iteration":848,"passed_time":0.6019778136,"remaining_time":0.1070655475},
{"learn":[4.706032324],"iteration":849,"passed_time":0.6027113058,"remaining_time":0.1063608187},
{"learn":[4.705109999],"iteration":850,"passed_time":0.6035078231,"remaining_time":0.1056670572},
{"learn":[4.704082869],"iteration":851,"passed_time":0.6043054896,"remaining_time":0.1049732541},
{"learn":[4.703273299],"iteration":852,"passed_time":0.6054475245,"remaining_time":0.1043385535},
{"learn":[4.702239187],"iteration":853,"passed_time":0.606344871,"remaining_time":0.1036608327},
{"learn":[4.701953272],"iteration":854,"passed_time":0.6071900023,"remaining_time":0.1029737431},
{"learn":[4.701302607],"iteration":855,"passed_time":0.6080320252,"remaining_time":0.1022857612},
{"learn":[4.700482446],"iteration":856,"passed_time":0.6087267379,"remaining_time":0.1015728396},
{"learn":[4.699736199],"iteration":857,"passed_time":0.6094400719,"remaining_time":0.1008630422},
{"learn":[4.69899539],"iteration":858,"passed_time":0.6102810966,"remaining_time":0.1001741963},
{"learn":[4.698243073],"iteration":859,"passed_time":0.610957897,"remaining_time":0.0994582623},
{"learn":[4.698209932],"iteration":860,"passed_time":0.6113025535,"remaining_time":0.09868879784},
{"learn":[4.697870801],"iteration":861,"passed_time":0.6119497432,"remaining_time":0.09796875239},
{"learn":[4.69664589],"iteration":862,"passed_time":0.6126231313,"remaining_time":0.09725303475},
{"learn":[4.69573773],"iteration":863,"passed_time":0.6132541873,"remaining_time":0.0965307517},
{"learn":[4.695090103],"iteration":864,"passed_time":0.6139282781,"remaining_time":0.095815396},
{"learn":[4.693901139],"iteration":865,"passed_time":0.6145671899,"remaining_time":0.0950946922},
{"learn":[4.693446568],"iteration":866,"passed_time":0.6152119308,"remaining_time":0.09437507128},
{"learn":[4.692510896],"iteration":867,"passed_time":0.6158736317,"remaining_time":0.09365820206},
{"learn":[4.690747828],"iteration":868,"passed_time":0.6165712706,"remaining_time":0.09294687739},
{"learn":[4.689888563],"iteration":869,"passed_time":0.6172230882,"remaining_time":0.09222873732},
{"learn":[4.689702963],"iteration":870,"passed_time":0.6178515971,"remaining_time":0.09150729739},
{"learn":[4.6889871],"iteration":871,"passed_time":0.6185438425,"remaining_time":0.09079542642},
{"learn":[4.688295659],"iteration":872,"passed_time":0.6192000247,"remaining_time":0.09007835411},
{"learn":[4.68775527],"iteration":873,"passed_time":0.6198765858,"remaining_time":0.08936435905},
{"learn":[4.686960555],"iteration":874,"passed_time":0.6205260117,"remaining_time":0.0886465731},
{"learn":[4.68565346],"iteration":875,"passed_time":0.6211777838,"remaining_time":0.08792927533},
{"learn":[4.685333507],"iteration":876,"passed_time":0.6218059649,"remaining_time":0.08720881833},
{"learn":[4.684816365],"iteration":877,"passed_time":0.6224104937,"remaining_time":0.086485285},
{"learn":[4.683827439],"iteration":878,"passed_time":0.6230221244,"remaining_time":0.08576300006},
{"learn":[4.683371007],"iteration":879,"passed_time":0.6236384451,"remaining_time":0.08504160614},
{"learn":[4.681833509],"iteration":880,"passed_time":0.6242772779,"remaining_time":0.08432349156},
{"learn":[4.680889935],"iteration":881,"passed_time":0.6248718903,"remaining_time":0.08359964065},
{"learn":[4.679303311],"iteration":882,"passed_time":0.6254856399,"remaining_time":0.0828786182},
{"learn":[4.679196139],"iteration":883,"passed_time":0.6260570796,"remaining_time":0.08215228646},
{"learn":[4.677902114],"iteration":884,"passed_time":0.6267211569,"remaining_time":0.08143834242},
{"learn":[4.677871425],"iteration":885,"passed_time":0.6270264037,"remaining_time":0.08067834088},
{"learn":[4.677348891],"iteration":886,"passed_time":0.6277039212,"remaining_time":0.07996679042},
{"learn":[4.67683957],"iteration":887,"passed_time":0.6283984294,"remaining_time":0.07925745956},
{"learn":[4.676164435],"iteration":888,"passed_time":0.6292777361,"remaining_time":0.0785712359},
{"learn":[4.674700451],"iteration":889,"passed_time":0.6300815141,"remaining_time":0.07787524331},
{"learn":[4.674289353],"iteration":890,"passed_time":0.6308882649,"remaining_time":0.07717937247},
{"learn":[4.673549187],"iteration":891,"passed_time":0.6316771653,"remaining_time":0.07648109177},
{"learn":[4.672533321],"iteration":892,"passed_time":0.6324415348,"remaining_time":0.07577966878},
{"learn":[4.671853333],"iteration":893,"passed_time":0.6332005153,"remaining_time":0.07507746602},
{"learn":[4.670865583],"iteration":894,"passed_time":0.6338508828,"remaining_time":0.07436239407},
{"learn":[4.670524619],"iteration":895,"passed_time":0.634592733,"remaining_time":0.07365808508},
{"learn":[4.670399063],"iteration":896,"passed_time":0.6352364137,"remaining_time":0.07294241985},
{"learn":[4.669735317],"iteration":897,"passed_time":0.6360006806,"remaining_time":0.07224061183},
{"learn":[4.668724169],"iteration":898,"passed_time":0.6367631573,"remaining_time":0.07153846372},
{"learn":[4.667459904],"iteration":899,"passed_time":0.6374206932,"remaining_time":0.07082452147},
{"learn":[4.666779978],"iteration":900,"passed_time":0.6380573588,"remaining_time":0.07010841123},
{"learn":[4.665290864],"iteration":901,"passed_time":0.6387087312,"remaining_time":0.06939407501},
{"learn":[4.664735559],"iteration":902,"passed_time":0.639394377,"remaining_time":0.06868355988},
{"learn":[4.663512443],"iteration":903,"passed_time":0.6400068241,"remaining_time":0.06796532645},
{"learn":[4.663013644],"iteration":904,"passed_time":0.6406355008,"remaining_time":0.06724903047},
{"learn":[4.66108808],"iteration":905,"passed_time":0.6412816541,"remaining_time":0.06653474116},
{"learn":[4.659936592],"iteration":906,"passed_time":0.6420038786,"remaining_time":0.06582840211},
{"learn":[4.659192896],"iteration":907,"passed_time":0.6427165905,"remaining_time":0.06512106424},
{"learn":[4.658097221],"iteration":908,"passed_time":0.6435331676,"remaining_time":0.06442411249},
{"learn":[4.657602077],"iteration":909,"passed_time":0.6443705407,"remaining_time":0.06372895457},
{"learn":[4.65691977],"iteration":910,"passed_time":0.6450580801,"remaining_time":0.06301884646},
{"learn":[4.656230158],"iteration":911,"passed_time":0.645791194,"remaining_time":0.06231318539},
{"learn":[4.655705079],"iteration":912,"passed_time":0.6464398982,"remaining_time":0.06159942075},
{"learn":[4.655172286],"iteration":913,"passed_time":0.6471239199,"remaining_time":0.06088912157},
{"learn":[4.654992944],"iteration":914,"passed_time":0.6477964818,"remaining_time":0.06017781524},
{"learn":[4.654425172],"iteration":915,"passed_time":0.648438223,"remaining_time":0.05946376717},
{"learn":[4.653538616],"iteration":916,"passed_time":0.6490863555,"remaining_time":0.05875045529},
{"learn":[4.652696259],"iteration":917,"passed_time":0.6497600714,"remaining_time":0.05803957065},
{"learn":[4.652066563],"iteration":918,"passed_time":0.6505313823,"remaining_time":0.05733736884},
{"learn":[4.65159162],"iteration":919,"passed_time":0.6511891022,"remaining_time":0.05662513932},
{"learn":[4.651382226],"iteration":920,"passed_time":0.6517902002,"remaining_time":0.05590817135},
{"learn":[4.650612639],"iteration":921,"passed_time":0.6525967398,"remaining_time":0.05520883482},
{"learn":[4.649776317],"iteration":922,"passed_time":0.6533066963,"remaining_time":0.05450120868},
{"learn":[4.647726739],"iteration":923,"passed_time":0.6541022757,"remaining_time":0.05380062008},
{"learn":[4.647312244],"iteration":924,"passed_time":0.6548252761,"remaining_time":0.0530939413},
{"learn":[4.646465017],"iteration":925,"passed_time":0.6557618591,"remaining_time":0.05240429543},
{"learn":[4.64533902],"iteration":926,"passed_time":0.6564724633,"remaining_time":0.05169632127},
{"learn":[4.644523945],"iteration":927,"passed_time":0.6571958654,"remaining_time":0.05098933439},
{"learn":[4.643932186],"iteration":928,"passed_time":0.6578540028,"remaining_time":0.05027732422},
{"learn":[4.643112184],"iteration":929,"passed_time":0.6586092635,"remaining_time":0.04957274027},
{"learn":[4.642563299],"iteration":930,"passed_time":0.6592931559,"remaining_time":0.04886275806},
{"learn":[4.641763215],"iteration":931,"passed_time":0.6600635615,"remaining_time":0.04815914397},
{"learn":[4.640953194],"iteration":932,"passed_time":0.6609414434,"remaining_time":0.04746310473},
{"learn":[4.640790508],"iteration":933,"passed_time":0.6616572398,"remaining_time":0.04675522251},
{"learn":[4.639991894],"iteration":934,"passed_time":0.6623456919,"remaining_time":0.04604542243},
{"learn":[4.639339219],"iteration":935,"passed_time":0.6630698158,"remaining_time":0.04533810706},
{"learn":[4.638419181],"iteration":936,"passed_time":0.6638494744,"remaining_time":0.04463448974},
{"learn":[4.637590291],"iteration":937,"passed_time":0.6645173951,"remaining_time":0.04392332462},
{"learn":[4.63700092],"iteration":938,"passed_time":0.6652128002,"remaining_time":0.04321403707},
{"learn":[4.636422225],"iteration":939,"passed_time":0.6659223814,"remaining_time":0.04250568392},
{"learn":[4.636143022],"iteration":940,"passed_time":0.6666784494,"remaining_time":0.04180024284},
{"learn":[4.635073582],"iteration":941,"passed_time":0.6673931082,"remaining_time":0.04109214467},
{"learn":[4.634929354],"iteration":942,"passed_time":0.6681060591,"remaining_time":0.04038392934},
{"learn":[4.634459802],"iteration":943,"passed_time":0.6689223456,"remaining_time":0.03968183406},
{"learn":[4.634361034],"iteration":944,"passed_time":0.6697407125,"remaining_time":0.03897961819},
{"learn":[4.634261064],"iteration":945,"passed_time":0.6704646508,"remaining_time":0.03827176653},
{"learn":[4.633550983],"iteration":946,"passed_time":0.6713193781,"remaining_time":0.03757120068},
{"learn":[4.632394626],"iteration":947,"passed_time":0.6722543507,"remaining_time":0.03687471122},
{"learn":[4.63170274],"iteration":948,"passed_time":0.6729751636,"remaining_time":0.03616621005},
{"learn":[4.630919349],"iteration":949,"passed_time":0.6736535918,"remaining_time":0.0354554522},
{"learn":[4.630107668],"iteration":950,"passed_time":0.6743298569,"remaining_time":0.03474465088},
{"learn":[4.629345498],"iteration":951,"passed_time":0.6750559036,"remaining_time":0.03403643212},
{"learn":[4.627262917],"iteration":952,"passed_time":0.6757155779,"remaining_time":0.03332490258},
{"learn":[4.626161896],"iteration":953,"passed_time":0.6764316062,"remaining_time":0.03261619904},
{"learn":[4.624878939],"iteration":954,"passed_time":0.6772142707,"remaining_time":0.03191062009},
{"learn":[4.623983796],"iteration":955,"passed_time":0.6779270174,"remaining_time":0.03120166189},
{"learn":[4.623494575],"iteration":956,"passed_time":0.6786860524,"remaining_time":0.03049477561},
{"learn":[4.622532026],"iteration":957,"passed_time":0.6793814096,"remaining_time":0.02978498873},
{"learn":[4.621422829],"iteration":958,"passed_time":0.6800679065,"remaining_time":0.02907485315},
{"learn":[4.620687301],"iteration":959,"passed_time":0.680813424,"remaining_time":0.028367226},
{"learn":[4.620465764],"iteration":960,"passed_time":0.6814315634,"remaining_time":0.02765435065},
{"learn":[4.620083249],"iteration":961,"passed_time":0.6820787742,"remaining_time":0.0269428206},
{"learn":[4.619347375],"iteration":962,"passed_time":0.682765345,"remaining_time":0.02623293641},
{"learn":[4.618757921],"iteration":963,"passed_time":0.6833624942,"remaining_time":0.0255197612},
{"learn":[4.618678824],"iteration":964,"passed_time":0.6840378669,"remaining_time":0.02480966357},
{"learn":[4.617571325],"iteration":965,"passed_time":0.684672691,"remaining_time":0.02409821066},
{"learn":[4.616744738],"iteration":966,"passed_time":0.6853772392,"remaining_time":0.02338929565},
{"learn":[4.616062865],"iteration":967,"passed_time":0.6860077565,"remaining_time":0.02267794236},
{"learn":[4.615469056],"iteration":968,"passed_time":0.6866824476,"remaining_time":0.02196816912},
{"learn":[4.614142182],"iteration":969,"passed_time":0.687399606,"remaining_time":0.02125978163},
{"learn":[4.61355511],"iteration":970,"passed_time":0.6880971572,"remaining_time":0.02055079048},
{"learn":[4.613147425],"iteration":971,"passed_time":0.689038238,"remaining_time":0.01984883813},
{"learn":[4.612413129],"iteration":972,"passed_time":0.6897614309,"remaining_time":0.01914034803},
{"learn":[4.61175764],"iteration":973,"passed_time":0.6904429324,"remaining_time":0.01843071483},
{"learn":[4.611107139],"iteration":974,"passed_time":0.6910813833,"remaining_time":0.01772003547},
{"learn":[4.610657621],"iteration":975,"passed_time":0.691746778,"remaining_time":0.01701016667},
{"learn":[4.609599788],"iteration":976,"passed_time":0.6924080147,"remaining_time":0.01630029103},
{"learn":[4.609151221],"iteration":977,"passed_time":0.6930356758,"remaining_time":0.01558975958},
{"learn":[4.608627407],"iteration":978,"passed_time":0.6937078594,"remaining_time":0.01488035245},
{"learn":[4.607191341],"iteration":979,"passed_time":0.6943369035,"remaining_time":0.01417014089},
{"learn":[4.607037481],"iteration":980,"passed_time":0.6950356486,"remaining_time":0.01346144477},
{"learn":[4.606337488],"iteration":981,"passed_time":0.69591032,"remaining_time":0.01275599364},
{"learn":[4.605827366],"iteration":982,"passed_time":0.6966649263,"remaining_time":0.01204812182},
{"learn":[4.605066862],"iteration":983,"passed_time":0.6975987266,"remaining_time":0.01134306873},
{"learn":[4.604809393],"iteration":984,"passed_time":0.6984115236,"remaining_time":0.01063570848},
{"learn":[4.604551179],"iteration":985,"passed_time":0.6992161816,"remaining_time":0.009928018805},
{"learn":[4.604401493],"iteration":986,"passed_time":0.7002756524,"remaining_time":0.009223488836},
{"learn":[4.602960605],"iteration":987,"passed_time":0.7010578172,"remaining_time":0.008514872273},
{"learn":[4.602550465],"iteration":988,"passed_time":0.7017995806,"remaining_time":0.00780565762},
{"learn":[4.602032229],"iteration":989,"passed_time":0.7026253846,"remaining_time":0.007097226107},
{"learn":[4.601222679],"iteration":990,"passed_time":0.7033325427,"remaining_time":0.006387480206},
{"learn":[4.600558533],"iteration":991,"passed_time":0.704131522,"remaining_time":0.005678480016},
{"learn":[4.600105891],"iteration":992,"passed_time":0.704863238,"remaining_time":0.004968824437},
{"learn":[4.599338023],"iteration":993,"passed_time":0.7056266124,"remaining_time":0.004259315568},
{"learn":[4.598636072],"iteration":994,"passed_time":0.7063542655,"remaining_time":0.003549518922},
{"learn":[4.598070443],"iteration":995,"passed_time":0.7070465205,"remaining_time":0.002839544259},
{"learn":[4.598043758],"iteration":996,"passed_time":0.7075473024,"remaining_time":0.002129028994},
{"learn":[4.597624197],"iteration":997,"passed_time":0.7082595902,"remaining_time":0.001419357896},
{"learn":[4.597219678],"iteration":998,"passed_time":0.7089463806,"remaining_time":0.0007096560366},
{"learn":[4.596450536],"iteration":999,"passed_time":0.7095977637,"remaining_time":0}
]}